{
    "478": {
        "Index": "478",
        "ID": "355",
        "Name": "Mukhamadmurod Abdurakhmonov",
        "Sex": "M",
        "Age": "29.0",
        "Height": "192.0",
        "Weight": "117.0",
        "Team": "Tajikistan",
        "NOC": "TJK",
        "Games": "2016 Summer",
        "Year": "2016",
        "Season": "Summer",
        "City": "Rio de Janeiro",
        "Sport": "Judo",
        "Event": "Judo Men's Heavyweight",
        "Medal": "",
        "Host": "0",
        "Nat_Pop": "8734951.0",
        "Global_Pop%": "0.001173716",
        "Rural_Pop%": "73.109",
        "Life_Expect": "71.051",
        "GDP": "6951657159.0",
        "GDP_Per_Cap": "795.8438644",
        "Global_GDP%": "9.17e-05"
    },
    "480": {
        "Index": "480",
        "ID": "357",
        "Name": "Yusup Abdusalomov",
        "Sex": "M",
        "Age": "26.0",
        "Height": "170.0",
        "Weight": "84.0",
        "Team": "Tajikistan",
        "NOC": "TJK",
        "Games": "2004 Summer",
        "Year": "2004",
        "Season": "Summer",
        "City": "Athina",
        "Sport": "Wrestling",
        "Event": "Wrestling Men's Middleweight, Freestyle",
        "Medal": "",
        "Host": "0",
        "Nat_Pop": "6712841.0",
        "Global_Pop%": "0.001042958",
        "Rural_Pop%": "73.583",
        "Life_Expect": "67.163",
        "GDP": "2076148696.0",
        "GDP_Per_Cap": "309.2801835",
        "Global_GDP%": "4.74e-05"
    },
    "481": {
        "Index": "481",
        "ID": "357",
        "Name": "Yusup Abdusalomov",
        "Sex": "M",
        "Age": "30.0",
        "Height": "170.0",
        "Weight": "84.0",
        "Team": "Tajikistan",
        "NOC": "TJK",
        "Games": "2008 Summer",
        "Year": "2008",
        "Season": "Summer",
        "City": "Beijing",
        "Sport": "Wrestling",
        "Event": "Wrestling Men's Light-Heavyweight, Freestyle",
        "Medal": "Silver",
        "Host": "0",
        "Nat_Pop": "7309728.0",
        "Global_Pop%": "0.001080722",
        "Rural_Pop%": "73.517",
        "Life_Expect": "68.902",
        "GDP": "5161336170.0",
        "GDP_Per_Cap": "706.0914127",
        "Global_GDP%": "8.13e-05"
    },
    "482": {
        "Index": "482",
        "ID": "357",
        "Name": "Yusup Abdusalomov",
        "Sex": "M",
        "Age": "34.0",
        "Height": "170.0",
        "Weight": "84.0",
        "Team": "Tajikistan",
        "NOC": "TJK",
        "Games": "2012 Summer",
        "Year": "2012",
        "Season": "Summer",
        "City": "London",
        "Sport": "Wrestling",
        "Event": "Wrestling Men's Light-Heavyweight, Freestyle",
        "Medal": "",
        "Host": "0",
        "Nat_Pop": "7995062.0",
        "Global_Pop%": "0.001126477",
        "Rural_Pop%": "73.432",
        "Life_Expect": "70.234",
        "GDP": "7633049792.0",
        "GDP_Per_Cap": "954.7205252",
        "Global_GDP%": "0.00010191"
    },
    "3964": {
        "Index": "3964",
        "ID": "2766",
        "Name": "Shomil Aliyev",
        "Sex": "M",
        "Age": "24.0",
        "Height": "173.0",
        "Weight": "84.0",
        "Team": "Tajikistan",
        "NOC": "TJK",
        "Games": "2004 Summer",
        "Year": "2004",
        "Season": "Summer",
        "City": "Athina",
        "Sport": "Wrestling",
        "Event": "Wrestling Men's Light-Heavyweight, Freestyle",
        "Medal": "",
        "Host": "0",
        "Nat_Pop": "6712841.0",
        "Global_Pop%": "0.001042958",
        "Rural_Pop%": "73.583",
        "Life_Expect": "67.163",
        "GDP": "2076148696.0",
        "GDP_Per_Cap": "309.2801835",
        "Global_GDP%": "4.74e-05"
    },
    "8111": {
        "Index": "8111",
        "ID": "5672",
        "Name": "Ne'matullo Asronqulov",
        "Sex": "M",
        "Age": "26.0",
        "Height": "188.0",
        "Weight": "90.0",
        "Team": "Tajikistan",
        "NOC": "TJK",
        "Games": "2008 Summer",
        "Year": "2008",
        "Season": "Summer",
        "City": "Beijing",
        "Sport": "Judo",
        "Event": "Judo Men's Middleweight",
        "Medal": "",
        "Host": "0",
        "Nat_Pop": "7309728.0",
        "Global_Pop%": "0.001080722",
        "Rural_Pop%": "73.517",
        "Life_Expect": "68.902",
        "GDP": "5161336170.0",
        "GDP_Per_Cap": "706.0914127",
        "Global_GDP%": "8.13e-05"
    },
    "9311": {
        "Index": "9311",
        "ID": "6461",
        "Name": "Sergey Babikov",
        "Sex": "M",
        "Age": "36.0",
        "Height": "170.0",
        "Weight": "100.0",
        "Team": "Tajikistan",
        "NOC": "TJK",
        "Games": "2004 Summer",
        "Year": "2004",
        "Season": "Summer",
        "City": "Athina",
        "Sport": "Shooting",
        "Event": "Shooting Men's Air Pistol, 10 metres",
        "Medal": "",
        "Host": "0",
        "Nat_Pop": "6712841.0",
        "Global_Pop%": "0.001042958",
        "Rural_Pop%": "73.583",
        "Life_Expect": "67.163",
        "GDP": "2076148696.0",
        "GDP_Per_Cap": "309.2801835",
        "Global_GDP%": "4.74e-05"
    },
    "9312": {
        "Index": "9312",
        "ID": "6461",
        "Name": "Sergey Babikov",
        "Sex": "M",
        "Age": "40.0",
        "Height": "170.0",
        "Weight": "100.0",
        "Team": "Tajikistan",
        "NOC": "TJK",
        "Games": "2008 Summer",
        "Year": "2008",
        "Season": "Summer",
        "City": "Beijing",
        "Sport": "Shooting",
        "Event": "Shooting Men's Air Pistol, 10 metres",
        "Medal": "",
        "Host": "0",
        "Nat_Pop": "7309728.0",
        "Global_Pop%": "0.001080722",
        "Rural_Pop%": "73.517",
        "Life_Expect": "68.902",
        "GDP": "5161336170.0",
        "GDP_Per_Cap": "706.0914127",
        "Global_GDP%": "8.13e-05"
    },
    "9313": {
        "Index": "9313",
        "ID": "6461",
        "Name": "Sergey Babikov",
        "Sex": "M",
        "Age": "40.0",
        "Height": "170.0",
        "Weight": "100.0",
        "Team": "Tajikistan",
        "NOC": "TJK",
        "Games": "2008 Summer",
        "Year": "2008",
        "Season": "Summer",
        "City": "Beijing",
        "Sport": "Shooting",
        "Event": "Shooting Men's Free Pistol, 50 metres",
        "Medal": "",
        "Host": "0",
        "Nat_Pop": "7309728.0",
        "Global_Pop%": "0.001080722",
        "Rural_Pop%": "73.517",
        "Life_Expect": "68.902",
        "GDP": "5161336170.0",
        "GDP_Per_Cap": "706.0914127",
        "Global_GDP%": "8.13e-05"
    },
    "9314": {
        "Index": "9314",
        "ID": "6461",
        "Name": "Sergey Babikov",
        "Sex": "M",
        "Age": "44.0",
        "Height": "170.0",
        "Weight": "100.0",
        "Team": "Tajikistan",
        "NOC": "TJK",
        "Games": "2012 Summer",
        "Year": "2012",
        "Season": "Summer",
        "City": "London",
        "Sport": "Shooting",
        "Event": "Shooting Men's Air Pistol, 10 metres",
        "Medal": "",
        "Host": "0",
        "Nat_Pop": "7995062.0",
        "Global_Pop%": "0.001126477",
        "Rural_Pop%": "73.432",
        "Life_Expect": "70.234",
        "GDP": "7633049792.0",
        "GDP_Per_Cap": "954.7205252",
        "Global_GDP%": "0.00010191"
    },
    "19376": {
        "Index": "19376",
        "ID": "13375",
        "Name": "Rasul Boqiev",
        "Sex": "M",
        "Age": "25.0",
        "Height": "175.0",
        "Weight": "73.0",
        "Team": "Tajikistan",
        "NOC": "TJK",
        "Games": "2008 Summer",
        "Year": "2008",
        "Season": "Summer",
        "City": "Beijing",
        "Sport": "Judo",
        "Event": "Judo Men's Lightweight",
        "Medal": "Bronze",
        "Host": "0",
        "Nat_Pop": "7309728.0",
        "Global_Pop%": "0.001080722",
        "Rural_Pop%": "73.517",
        "Life_Expect": "68.902",
        "GDP": "5161336170.0",
        "GDP_Per_Cap": "706.0914127",
        "Global_GDP%": "8.13e-05"
    },
    "19377": {
        "Index": "19377",
        "ID": "13375",
        "Name": "Rasul Boqiev",
        "Sex": "M",
        "Age": "29.0",
        "Height": "175.0",
        "Weight": "73.0",
        "Team": "Tajikistan",
        "NOC": "TJK",
        "Games": "2012 Summer",
        "Year": "2012",
        "Season": "Summer",
        "City": "London",
        "Sport": "Judo",
        "Event": "Judo Men's Lightweight",
        "Medal": "",
        "Host": "0",
        "Nat_Pop": "7995062.0",
        "Global_Pop%": "0.001126477",
        "Rural_Pop%": "73.432",
        "Life_Expect": "70.234",
        "GDP": "7633049792.0",
        "GDP_Per_Cap": "954.7205252",
        "Global_GDP%": "0.00010191"
    },
    "19378": {
        "Index": "19378",
        "ID": "13376",
        "Name": "Rustam Boqiev",
        "Sex": "M",
        "Age": "18.0",
        "Height": "",
        "Weight": "",
        "Team": "Tajikistan",
        "NOC": "TJK",
        "Games": "1996 Summer",
        "Year": "1996",
        "Season": "Summer",
        "City": "Atlanta",
        "Sport": "Judo",
        "Event": "Judo Men's Extra-Lightweight",
        "Medal": "",
        "Host": "0",
        "Nat_Pop": "5849540.0",
        "Global_Pop%": "0.001009835",
        "Rural_Pop%": "71.662",
        "Life_Expect": "63.618",
        "GDP": "1043893063.0",
        "GDP_Per_Cap": "178.4572912",
        "Global_GDP%": "3.3e-05"
    },
    "20964": {
        "Index": "20964",
        "ID": "14420",
        "Name": "Sheral Bozorov",
        "Sex": "M",
        "Age": "26.0",
        "Height": "180.0",
        "Weight": "81.0",
        "Team": "Tajikistan",
        "NOC": "TJK",
        "Games": "2008 Summer",
        "Year": "2008",
        "Season": "Summer",
        "City": "Beijing",
        "Sport": "Judo",
        "Event": "Judo Men's Half-Middleweight",
        "Medal": "",
        "Host": "0",
        "Nat_Pop": "7309728.0",
        "Global_Pop%": "0.001080722",
        "Rural_Pop%": "73.517",
        "Life_Expect": "68.902",
        "GDP": "5161336170.0",
        "GDP_Per_Cap": "706.0914127",
        "Global_GDP%": "8.13e-05"
    },
    "30473": {
        "Index": "30473",
        "ID": "20790",
        "Name": "Alisher Chingizov",
        "Sex": "M",
        "Age": "22.0",
        "Height": "176.0",
        "Weight": "68.0",
        "Team": "Tajikistan",
        "NOC": "TJK",
        "Games": "2008 Summer",
        "Year": "2008",
        "Season": "Summer",
        "City": "Beijing",
        "Sport": "Swimming",
        "Event": "Swimming Men's 50 metres Freestyle",
        "Medal": "",
        "Host": "0",
        "Nat_Pop": "7309728.0",
        "Global_Pop%": "0.001080722",
        "Rural_Pop%": "73.517",
        "Life_Expect": "68.902",
        "GDP": "5161336170.0",
        "GDP_Per_Cap": "706.0914127",
        "Global_GDP%": "8.13e-05"
    },
    "31033": {
        "Index": "31033",
        "ID": "21147",
        "Name": "Mavzuna Chorieva",
        "Sex": "F",
        "Age": "19.0",
        "Height": "160.0",
        "Weight": "60.0",
        "Team": "Tajikistan",
        "NOC": "TJK",
        "Games": "2012 Summer",
        "Year": "2012",
        "Season": "Summer",
        "City": "London",
        "Sport": "Boxing",
        "Event": "Boxing Women's Lightweight",
        "Medal": "Bronze",
        "Host": "0",
        "Nat_Pop": "7995062.0",
        "Global_Pop%": "0.001126477",
        "Rural_Pop%": "73.432",
        "Life_Expect": "70.234",
        "GDP": "7633049792.0",
        "GDP_Per_Cap": "954.7205252",
        "Global_GDP%": "0.00010191"
    },
    "40472": {
        "Index": "40472",
        "ID": "28020",
        "Name": "Raul Dgvareli",
        "Sex": "M",
        "Age": "31.0",
        "Height": "189.0",
        "Weight": "130.0",
        "Team": "Tajikistan",
        "NOC": "TJK",
        "Games": "1996 Summer",
        "Year": "1996",
        "Season": "Summer",
        "City": "Atlanta",
        "Sport": "Wrestling",
        "Event": "Wrestling Men's Super-Heavyweight, Greco-Roman",
        "Medal": "",
        "Host": "0",
        "Nat_Pop": "5849540.0",
        "Global_Pop%": "0.001009835",
        "Rural_Pop%": "71.662",
        "Life_Expect": "63.618",
        "GDP": "1043893063.0",
        "GDP_Per_Cap": "178.4572912",
        "Global_GDP%": "3.3e-05"
    },
    "42114": {
        "Index": "42114",
        "ID": "29061",
        "Name": "Gulsara Dodoboeva",
        "Sex": "F",
        "Age": "20.0",
        "Height": "160.0",
        "Weight": "47.0",
        "Team": "Tajikistan",
        "NOC": "TJK",
        "Games": "1996 Summer",
        "Year": "1996",
        "Season": "Summer",
        "City": "Atlanta",
        "Sport": "Athletics",
        "Event": "Athletics Women's Marathon",
        "Medal": "",
        "Host": "0",
        "Nat_Pop": "5849540.0",
        "Global_Pop%": "0.001009835",
        "Rural_Pop%": "71.662",
        "Life_Expect": "63.618",
        "GDP": "1043893063.0",
        "GDP_Per_Cap": "178.4572912",
        "Global_GDP%": "3.3e-05"
    },
    "42115": {
        "Index": "42115",
        "ID": "29061",
        "Name": "Gulsara Dodoboeva",
        "Sex": "F",
        "Age": "24.0",
        "Height": "160.0",
        "Weight": "47.0",
        "Team": "Tajikistan",
        "NOC": "TJK",
        "Games": "2000 Summer",
        "Year": "2000",
        "Season": "Summer",
        "City": "Sydney",
        "Sport": "Athletics",
        "Event": "Athletics Women's Marathon",
        "Medal": "",
        "Host": "0",
        "Nat_Pop": "6216205.0",
        "Global_Pop%": "0.001016039",
        "Rural_Pop%": "73.514",
        "Life_Expect": "65.485",
        "GDP": "860550305.8",
        "GDP_Per_Cap": "138.4366033",
        "Global_GDP%": "2.56e-05"
    },
    "42116": {
        "Index": "42116",
        "ID": "29061",
        "Name": "Gulsara Dodoboeva",
        "Sex": "F",
        "Age": "28.0",
        "Height": "160.0",
        "Weight": "47.0",
        "Team": "Tajikistan",
        "NOC": "TJK",
        "Games": "2004 Summer",
        "Year": "2004",
        "Season": "Summer",
        "City": "Athina",
        "Sport": "Athletics",
        "Event": "Athletics Women's Marathon",
        "Medal": "",
        "Host": "0",
        "Nat_Pop": "6712841.0",
        "Global_Pop%": "0.001042958",
        "Rural_Pop%": "73.583",
        "Life_Expect": "67.163",
        "GDP": "2076148696.0",
        "GDP_Per_Cap": "309.2801835",
        "Global_GDP%": "4.74e-05"
    },
    "42988": {
        "Index": "42988",
        "ID": "29631",
        "Name": "Sheral Dostiev",
        "Sex": "M",
        "Age": "19.0",
        "Height": "164.0",
        "Weight": "52.0",
        "Team": "Tajikistan",
        "NOC": "TJK",
        "Games": "2004 Summer",
        "Year": "2004",
        "Season": "Summer",
        "City": "Athina",
        "Sport": "Boxing",
        "Event": "Boxing Men's Light-Flyweight",
        "Medal": "",
        "Host": "0",
        "Nat_Pop": "6712841.0",
        "Global_Pop%": "0.001042958",
        "Rural_Pop%": "73.583",
        "Life_Expect": "67.163",
        "GDP": "2076148696.0",
        "GDP_Per_Cap": "309.2801835",
        "Global_GDP%": "4.74e-05"
    },
    "42989": {
        "Index": "42989",
        "ID": "29631",
        "Name": "Sheral Dostiev",
        "Sex": "M",
        "Age": "23.0",
        "Height": "164.0",
        "Weight": "52.0",
        "Team": "Tajikistan",
        "NOC": "TJK",
        "Games": "2008 Summer",
        "Year": "2008",
        "Season": "Summer",
        "City": "Beijing",
        "Sport": "Boxing",
        "Event": "Boxing Men's Light-Flyweight",
        "Medal": "",
        "Host": "0",
        "Nat_Pop": "7309728.0",
        "Global_Pop%": "0.001080722",
        "Rural_Pop%": "73.517",
        "Life_Expect": "68.902",
        "GDP": "5161336170.0",
        "GDP_Per_Cap": "706.0914127",
        "Global_GDP%": "8.13e-05"
    },
    "43762": {
        "Index": "43762",
        "ID": "30151",
        "Name": "Andrey Drygin",
        "Sex": "M",
        "Age": "24.0",
        "Height": "180.0",
        "Weight": "82.0",
        "Team": "Tajikistan",
        "NOC": "TJK",
        "Games": "2002 Winter",
        "Year": "2002",
        "Season": "Winter",
        "City": "Salt Lake City",
        "Sport": "Alpine Skiing",
        "Event": "Alpine Skiing Men's Super G",
        "Medal": "",
        "Host": "0",
        "Nat_Pop": "6447688.0",
        "Global_Pop%": "0.001027221",
        "Rural_Pop%": "73.571",
        "Life_Expect": "66.303",
        "GDP": "1221113780.0",
        "GDP_Per_Cap": "189.3878519",
        "Global_GDP%": "3.53e-05"
    },
    "43763": {
        "Index": "43763",
        "ID": "30151",
        "Name": "Andrey Drygin",
        "Sex": "M",
        "Age": "24.0",
        "Height": "180.0",
        "Weight": "82.0",
        "Team": "Tajikistan",
        "NOC": "TJK",
        "Games": "2002 Winter",
        "Year": "2002",
        "Season": "Winter",
        "City": "Salt Lake City",
        "Sport": "Alpine Skiing",
        "Event": "Alpine Skiing Men's Giant Slalom",
        "Medal": "",
        "Host": "0",
        "Nat_Pop": "6447688.0",
        "Global_Pop%": "0.001027221",
        "Rural_Pop%": "73.571",
        "Life_Expect": "66.303",
        "GDP": "1221113780.0",
        "GDP_Per_Cap": "189.3878519",
        "Global_GDP%": "3.53e-05"
    },
    "43764": {
        "Index": "43764",
        "ID": "30151",
        "Name": "Andrey Drygin",
        "Sex": "M",
        "Age": "28.0",
        "Height": "180.0",
        "Weight": "82.0",
        "Team": "Tajikistan",
        "NOC": "TJK",
        "Games": "2006 Winter",
        "Year": "2006",
        "Season": "Winter",
        "City": "Torino",
        "Sport": "Alpine Skiing",
        "Event": "Alpine Skiing Men's Downhill",
        "Medal": "",
        "Host": "0",
        "Nat_Pop": "7000557.0",
        "Global_Pop%": "0.001060944",
        "Rural_Pop%": "73.55",
        "Life_Expect": "68.052",
        "GDP": "2830236054.0",
        "GDP_Per_Cap": "404.2872666",
        "Global_GDP%": "5.51e-05"
    },
    "43765": {
        "Index": "43765",
        "ID": "30151",
        "Name": "Andrey Drygin",
        "Sex": "M",
        "Age": "28.0",
        "Height": "180.0",
        "Weight": "82.0",
        "Team": "Tajikistan",
        "NOC": "TJK",
        "Games": "2006 Winter",
        "Year": "2006",
        "Season": "Winter",
        "City": "Torino",
        "Sport": "Alpine Skiing",
        "Event": "Alpine Skiing Men's Super G",
        "Medal": "",
        "Host": "0",
        "Nat_Pop": "7000557.0",
        "Global_Pop%": "0.001060944",
        "Rural_Pop%": "73.55",
        "Life_Expect": "68.052",
        "GDP": "2830236054.0",
        "GDP_Per_Cap": "404.2872666",
        "Global_GDP%": "5.51e-05"
    },
    "43766": {
        "Index": "43766",
        "ID": "30151",
        "Name": "Andrey Drygin",
        "Sex": "M",
        "Age": "28.0",
        "Height": "180.0",
        "Weight": "82.0",
        "Team": "Tajikistan",
        "NOC": "TJK",
        "Games": "2006 Winter",
        "Year": "2006",
        "Season": "Winter",
        "City": "Torino",
        "Sport": "Alpine Skiing",
        "Event": "Alpine Skiing Men's Giant Slalom",
        "Medal": "",
        "Host": "0",
        "Nat_Pop": "7000557.0",
        "Global_Pop%": "0.001060944",
        "Rural_Pop%": "73.55",
        "Life_Expect": "68.052",
        "GDP": "2830236054.0",
        "GDP_Per_Cap": "404.2872666",
        "Global_GDP%": "5.51e-05"
    },
    "43767": {
        "Index": "43767",
        "ID": "30151",
        "Name": "Andrey Drygin",
        "Sex": "M",
        "Age": "32.0",
        "Height": "180.0",
        "Weight": "82.0",
        "Team": "Tajikistan",
        "NOC": "TJK",
        "Games": "2010 Winter",
        "Year": "2010",
        "Season": "Winter",
        "City": "Vancouver",
        "Sport": "Alpine Skiing",
        "Event": "Alpine Skiing Men's Downhill",
        "Medal": "",
        "Host": "0",
        "Nat_Pop": "7641630.0",
        "Global_Pop%": "0.001102584",
        "Rural_Pop%": "73.484",
        "Life_Expect": "69.644",
        "GDP": "5642178580.0",
        "GDP_Per_Cap": "738.3475227",
        "Global_GDP%": "8.55e-05"
    },
    "43768": {
        "Index": "43768",
        "ID": "30151",
        "Name": "Andrey Drygin",
        "Sex": "M",
        "Age": "32.0",
        "Height": "180.0",
        "Weight": "82.0",
        "Team": "Tajikistan",
        "NOC": "TJK",
        "Games": "2010 Winter",
        "Year": "2010",
        "Season": "Winter",
        "City": "Vancouver",
        "Sport": "Alpine Skiing",
        "Event": "Alpine Skiing Men's Super G",
        "Medal": "",
        "Host": "0",
        "Nat_Pop": "7641630.0",
        "Global_Pop%": "0.001102584",
        "Rural_Pop%": "73.484",
        "Life_Expect": "69.644",
        "GDP": "5642178580.0",
        "GDP_Per_Cap": "738.3475227",
        "Global_GDP%": "8.55e-05"
    },
    "43769": {
        "Index": "43769",
        "ID": "30151",
        "Name": "Andrey Drygin",
        "Sex": "M",
        "Age": "32.0",
        "Height": "180.0",
        "Weight": "82.0",
        "Team": "Tajikistan",
        "NOC": "TJK",
        "Games": "2010 Winter",
        "Year": "2010",
        "Season": "Winter",
        "City": "Vancouver",
        "Sport": "Alpine Skiing",
        "Event": "Alpine Skiing Men's Giant Slalom",
        "Medal": "",
        "Host": "0",
        "Nat_Pop": "7641630.0",
        "Global_Pop%": "0.001102584",
        "Rural_Pop%": "73.484",
        "Life_Expect": "69.644",
        "GDP": "5642178580.0",
        "GDP_Per_Cap": "738.3475227",
        "Global_GDP%": "8.55e-05"
    },
    "43770": {
        "Index": "43770",
        "ID": "30151",
        "Name": "Andrey Drygin",
        "Sex": "M",
        "Age": "32.0",
        "Height": "180.0",
        "Weight": "82.0",
        "Team": "Tajikistan",
        "NOC": "TJK",
        "Games": "2010 Winter",
        "Year": "2010",
        "Season": "Winter",
        "City": "Vancouver",
        "Sport": "Alpine Skiing",
        "Event": "Alpine Skiing Men's Slalom",
        "Medal": "",
        "Host": "0",
        "Nat_Pop": "7641630.0",
        "Global_Pop%": "0.001102584",
        "Rural_Pop%": "73.484",
        "Life_Expect": "69.644",
        "GDP": "5642178580.0",
        "GDP_Per_Cap": "738.3475227",
        "Global_GDP%": "8.55e-05"
    },
    "64389": {
        "Index": "64389",
        "ID": "43836",
        "Name": "Alisher Gulov",
        "Sex": "M",
        "Age": "22.0",
        "Height": "189.0",
        "Weight": "84.0",
        "Team": "Tajikistan",
        "NOC": "TJK",
        "Games": "2012 Summer",
        "Year": "2012",
        "Season": "Summer",
        "City": "London",
        "Sport": "Taekwondo",
        "Event": "Taekwondo Men's Heavyweight",
        "Medal": "",
        "Host": "0",
        "Nat_Pop": "7995062.0",
        "Global_Pop%": "0.001126477",
        "Rural_Pop%": "73.432",
        "Life_Expect": "70.234",
        "GDP": "7633049792.0",
        "GDP_Per_Cap": "954.7205252",
        "Global_GDP%": "0.00010191"
    },
    "68054": {
        "Index": "68054",
        "ID": "46386",
        "Name": "Khurshed Hasanov",
        "Sex": "M",
        "Age": "22.0",
        "Height": "192.0",
        "Weight": "54.0",
        "Team": "Tajikistan",
        "NOC": "TJK",
        "Games": "1996 Summer",
        "Year": "1996",
        "Season": "Summer",
        "City": "Atlanta",
        "Sport": "Boxing",
        "Event": "Boxing Men's Bantamweight",
        "Medal": "",
        "Host": "0",
        "Nat_Pop": "5849540.0",
        "Global_Pop%": "0.001009835",
        "Rural_Pop%": "71.662",
        "Life_Expect": "63.618",
        "GDP": "1043893063.0",
        "GDP_Per_Cap": "178.4572912",
        "Global_GDP%": "3.3e-05"
    },
    "77259": {
        "Index": "77259",
        "ID": "52557",
        "Name": "Rustam Iskandari",
        "Sex": "M",
        "Age": "20.0",
        "Height": "176.0",
        "Weight": "96.0",
        "Team": "Tajikistan",
        "NOC": "TJK",
        "Games": "2012 Summer",
        "Year": "2012",
        "Season": "Summer",
        "City": "London",
        "Sport": "Wrestling",
        "Event": "Wrestling Men's Heavyweight, Freestyle",
        "Medal": "",
        "Host": "0",
        "Nat_Pop": "7995062.0",
        "Global_Pop%": "0.001126477",
        "Rural_Pop%": "73.432",
        "Life_Expect": "70.234",
        "GDP": "7633049792.0",
        "GDP_Per_Cap": "954.7205252",
        "Global_GDP%": "0.00010191"
    },
    "77750": {
        "Index": "77750",
        "ID": "52866",
        "Name": "Natalya Ivanova",
        "Sex": "F",
        "Age": "35.0",
        "Height": "163.0",
        "Weight": "63.0",
        "Team": "Tajikistan",
        "NOC": "TJK",
        "Games": "2004 Summer",
        "Year": "2004",
        "Season": "Summer",
        "City": "Athina",
        "Sport": "Wrestling",
        "Event": "Wrestling Women's Middleweight, Freestyle",
        "Medal": "",
        "Host": "0",
        "Nat_Pop": "6712841.0",
        "Global_Pop%": "0.001042958",
        "Rural_Pop%": "73.583",
        "Life_Expect": "67.163",
        "GDP": "2076148696.0",
        "GDP_Per_Cap": "309.2801835",
        "Global_GDP%": "4.74e-05"
    },
    "77969": {
        "Index": "77969",
        "ID": "53002",
        "Name": "Katerina Izmaylova",
        "Sex": "F",
        "Age": "23.0",
        "Height": "170.0",
        "Weight": "57.0",
        "Team": "Tajikistan",
        "NOC": "TJK",
        "Games": "2000 Summer",
        "Year": "2000",
        "Season": "Summer",
        "City": "Sydney",
        "Sport": "Swimming",
        "Event": "Swimming Women's 100 metres Freestyle",
        "Medal": "",
        "Host": "0",
        "Nat_Pop": "6216205.0",
        "Global_Pop%": "0.001016039",
        "Rural_Pop%": "73.514",
        "Life_Expect": "65.485",
        "GDP": "860550305.8",
        "GDP_Per_Cap": "138.4366033",
        "Global_GDP%": "2.56e-05"
    },
    "77970": {
        "Index": "77970",
        "ID": "53002",
        "Name": "Katerina Izmaylova",
        "Sex": "F",
        "Age": "31.0",
        "Height": "170.0",
        "Weight": "57.0",
        "Team": "Tajikistan",
        "NOC": "TJK",
        "Games": "2008 Summer",
        "Year": "2008",
        "Season": "Summer",
        "City": "Beijing",
        "Sport": "Swimming",
        "Event": "Swimming Women's 50 metres Freestyle",
        "Medal": "",
        "Host": "0",
        "Nat_Pop": "7309728.0",
        "Global_Pop%": "0.001080722",
        "Rural_Pop%": "73.517",
        "Life_Expect": "68.902",
        "GDP": "5161336170.0",
        "GDP_Per_Cap": "706.0914127",
        "Global_GDP%": "8.13e-05"
    },
    "77971": {
        "Index": "77971",
        "ID": "53002",
        "Name": "Katerina Izmaylova",
        "Sex": "F",
        "Age": "35.0",
        "Height": "170.0",
        "Weight": "57.0",
        "Team": "Tajikistan",
        "NOC": "TJK",
        "Games": "2012 Summer",
        "Year": "2012",
        "Season": "Summer",
        "City": "London",
        "Sport": "Swimming",
        "Event": "Swimming Women's 50 metres Freestyle",
        "Medal": "",
        "Host": "0",
        "Nat_Pop": "7995062.0",
        "Global_Pop%": "0.001126477",
        "Rural_Pop%": "73.432",
        "Life_Expect": "70.234",
        "GDP": "7633049792.0",
        "GDP_Per_Cap": "954.7205252",
        "Global_GDP%": "0.00010191"
    },
    "83885": {
        "Index": "83885",
        "ID": "57105",
        "Name": "Albina Kamoliddinova",
        "Sex": "F",
        "Age": "39.0",
        "Height": "160.0",
        "Weight": "70.0",
        "Team": "Tajikistan",
        "NOC": "TJK",
        "Games": "2008 Summer",
        "Year": "2008",
        "Season": "Summer",
        "City": "Beijing",
        "Sport": "Archery",
        "Event": "Archery Women's Individual",
        "Medal": "",
        "Host": "0",
        "Nat_Pop": "7309728.0",
        "Global_Pop%": "0.001080722",
        "Rural_Pop%": "73.517",
        "Life_Expect": "68.902",
        "GDP": "5161336170.0",
        "GDP_Per_Cap": "706.0914127",
        "Global_GDP%": "8.13e-05"
    },
    "84444": {
        "Index": "84444",
        "ID": "57457",
        "Name": "Lidiya Karamchakova",
        "Sex": "F",
        "Age": "36.0",
        "Height": "162.0",
        "Weight": "48.0",
        "Team": "Tajikistan",
        "NOC": "TJK",
        "Games": "2004 Summer",
        "Year": "2004",
        "Season": "Summer",
        "City": "Athina",
        "Sport": "Wrestling",
        "Event": "Wrestling Women's Flyweight, Freestyle",
        "Medal": "",
        "Host": "0",
        "Nat_Pop": "6712841.0",
        "Global_Pop%": "0.001042958",
        "Rural_Pop%": "73.583",
        "Life_Expect": "67.163",
        "GDP": "2076148696.0",
        "GDP_Per_Cap": "309.2801835",
        "Global_GDP%": "4.74e-05"
    },
    "93384": {
        "Index": "93384",
        "ID": "62924",
        "Name": "Vitaliy Koryakin",
        "Sex": "M",
        "Age": "24.0",
        "Height": "168.0",
        "Weight": "60.0",
        "Team": "Tajikistan",
        "NOC": "TJK",
        "Games": "2008 Summer",
        "Year": "2008",
        "Season": "Summer",
        "City": "Beijing",
        "Sport": "Wrestling",
        "Event": "Wrestling Men's Lightweight, Freestyle",
        "Medal": "",
        "Host": "0",
        "Nat_Pop": "7309728.0",
        "Global_Pop%": "0.001080722",
        "Rural_Pop%": "73.517",
        "Life_Expect": "68.902",
        "GDP": "5161336170.0",
        "GDP_Per_Cap": "706.0914127",
        "Global_GDP%": "8.13e-05"
    },
    "97082": {
        "Index": "97082",
        "ID": "65097",
        "Name": "Olim Kurbanov",
        "Sex": "M",
        "Age": "18.0",
        "Height": "186.0",
        "Weight": "69.0",
        "Team": "Tajikistan",
        "NOC": "TJK",
        "Games": "2016 Summer",
        "Year": "2016",
        "Season": "Summer",
        "City": "Rio de Janeiro",
        "Sport": "Swimming",
        "Event": "Swimming Men's 50 metres Freestyle",
        "Medal": "",
        "Host": "0",
        "Nat_Pop": "8734951.0",
        "Global_Pop%": "0.001173716",
        "Rural_Pop%": "73.109",
        "Life_Expect": "71.051",
        "GDP": "6951657159.0",
        "GDP_Per_Cap": "795.8438644",
        "Global_GDP%": "9.17e-05"
    },
    "120332": {
        "Index": "120332",
        "ID": "80525",
        "Name": "Galina Mityaeva",
        "Sex": "F",
        "Age": "17.0",
        "Height": "172.0",
        "Weight": "70.0",
        "Team": "Tajikistan",
        "NOC": "TJK",
        "Games": "2008 Summer",
        "Year": "2008",
        "Season": "Summer",
        "City": "Beijing",
        "Sport": "Athletics",
        "Event": "Athletics Women's Hammer Throw",
        "Medal": "",
        "Host": "0",
        "Nat_Pop": "7309728.0",
        "Global_Pop%": "0.001080722",
        "Rural_Pop%": "73.517",
        "Life_Expect": "68.902",
        "GDP": "5161336170.0",
        "GDP_Per_Cap": "706.0914127",
        "Global_GDP%": "8.13e-05"
    },
    "125511": {
        "Index": "125511",
        "ID": "83989",
        "Name": "Nargis Nabiyeva",
        "Sex": "F",
        "Age": "38.0",
        "Height": "168.0",
        "Weight": "60.0",
        "Team": "Tajikistan",
        "NOC": "TJK",
        "Games": "2004 Summer",
        "Year": "2004",
        "Season": "Summer",
        "City": "Athina",
        "Sport": "Archery",
        "Event": "Archery Women's Individual",
        "Medal": "",
        "Host": "0",
        "Nat_Pop": "6712841.0",
        "Global_Pop%": "0.001042958",
        "Rural_Pop%": "73.583",
        "Life_Expect": "67.163",
        "GDP": "2076148696.0",
        "GDP_Per_Cap": "309.2801835",
        "Global_GDP%": "4.74e-05"
    },
    "126894": {
        "Index": "126894",
        "ID": "84850",
        "Name": "Dilshod Nazarov",
        "Sex": "M",
        "Age": "22.0",
        "Height": "187.0",
        "Weight": "120.0",
        "Team": "Tajikistan",
        "NOC": "TJK",
        "Games": "2004 Summer",
        "Year": "2004",
        "Season": "Summer",
        "City": "Athina",
        "Sport": "Athletics",
        "Event": "Athletics Men's Hammer Throw",
        "Medal": "",
        "Host": "0",
        "Nat_Pop": "6712841.0",
        "Global_Pop%": "0.001042958",
        "Rural_Pop%": "73.583",
        "Life_Expect": "67.163",
        "GDP": "2076148696.0",
        "GDP_Per_Cap": "309.2801835",
        "Global_GDP%": "4.74e-05"
    },
    "126895": {
        "Index": "126895",
        "ID": "84850",
        "Name": "Dilshod Nazarov",
        "Sex": "M",
        "Age": "26.0",
        "Height": "187.0",
        "Weight": "120.0",
        "Team": "Tajikistan",
        "NOC": "TJK",
        "Games": "2008 Summer",
        "Year": "2008",
        "Season": "Summer",
        "City": "Beijing",
        "Sport": "Athletics",
        "Event": "Athletics Men's Hammer Throw",
        "Medal": "",
        "Host": "0",
        "Nat_Pop": "7309728.0",
        "Global_Pop%": "0.001080722",
        "Rural_Pop%": "73.517",
        "Life_Expect": "68.902",
        "GDP": "5161336170.0",
        "GDP_Per_Cap": "706.0914127",
        "Global_GDP%": "8.13e-05"
    },
    "126896": {
        "Index": "126896",
        "ID": "84850",
        "Name": "Dilshod Nazarov",
        "Sex": "M",
        "Age": "30.0",
        "Height": "187.0",
        "Weight": "120.0",
        "Team": "Tajikistan",
        "NOC": "TJK",
        "Games": "2012 Summer",
        "Year": "2012",
        "Season": "Summer",
        "City": "London",
        "Sport": "Athletics",
        "Event": "Athletics Men's Hammer Throw",
        "Medal": "",
        "Host": "0",
        "Nat_Pop": "7995062.0",
        "Global_Pop%": "0.001126477",
        "Rural_Pop%": "73.432",
        "Life_Expect": "70.234",
        "GDP": "7633049792.0",
        "GDP_Per_Cap": "954.7205252",
        "Global_GDP%": "0.00010191"
    },
    "126897": {
        "Index": "126897",
        "ID": "84850",
        "Name": "Dilshod Nazarov",
        "Sex": "M",
        "Age": "34.0",
        "Height": "187.0",
        "Weight": "120.0",
        "Team": "Tajikistan",
        "NOC": "TJK",
        "Games": "2016 Summer",
        "Year": "2016",
        "Season": "Summer",
        "City": "Rio de Janeiro",
        "Sport": "Athletics",
        "Event": "Athletics Men's Hammer Throw",
        "Medal": "Gold",
        "Host": "0",
        "Nat_Pop": "8734951.0",
        "Global_Pop%": "0.001173716",
        "Rural_Pop%": "73.109",
        "Life_Expect": "71.051",
        "GDP": "6951657159.0",
        "GDP_Per_Cap": "795.8438644",
        "Global_GDP%": "9.17e-05"
    },
    "126899": {
        "Index": "126899",
        "ID": "84853",
        "Name": "Sobirjon Nazarov",
        "Sex": "M",
        "Age": "21.0",
        "Height": "178.0",
        "Weight": "75.0",
        "Team": "Tajikistan",
        "NOC": "TJK",
        "Games": "2012 Summer",
        "Year": "2012",
        "Season": "Summer",
        "City": "London",
        "Sport": "Boxing",
        "Event": "Boxing Men's Middleweight",
        "Medal": "",
        "Host": "0",
        "Nat_Pop": "7995062.0",
        "Global_Pop%": "0.001126477",
        "Rural_Pop%": "73.432",
        "Life_Expect": "70.234",
        "GDP": "7633049792.0",
        "GDP_Per_Cap": "954.7205252",
        "Global_GDP%": "0.00010191"
    },
    "126945": {
        "Index": "126945",
        "ID": "84870",
        "Name": "Khayrullo Nazriev",
        "Sex": "M",
        "Age": "23.0",
        "Height": "",
        "Weight": "",
        "Team": "Tajikistan",
        "NOC": "TJK",
        "Games": "1996 Summer",
        "Year": "1996",
        "Season": "Summer",
        "City": "Atlanta",
        "Sport": "Judo",
        "Event": "Judo Men's Half-Heavyweight",
        "Medal": "",
        "Host": "0",
        "Nat_Pop": "5849540.0",
        "Global_Pop%": "0.001009835",
        "Rural_Pop%": "71.662",
        "Life_Expect": "63.618",
        "GDP": "1043893063.0",
        "GDP_Per_Cap": "178.4572912",
        "Global_GDP%": "3.3e-05"
    },
    "127073": {
        "Index": "127073",
        "ID": "84949",
        "Name": "Farhod Ne'matov",
        "Sex": "M",
        "Age": "22.0",
        "Height": "188.0",
        "Weight": "74.0",
        "Team": "Tajikistan",
        "NOC": "TJK",
        "Games": "2012 Summer",
        "Year": "2012",
        "Season": "Summer",
        "City": "London",
        "Sport": "Taekwondo",
        "Event": "Taekwondo Men's Welterweight",
        "Medal": "",
        "Host": "0",
        "Nat_Pop": "7995062.0",
        "Global_Pop%": "0.001126477",
        "Rural_Pop%": "73.432",
        "Life_Expect": "70.234",
        "GDP": "7633049792.0",
        "GDP_Per_Cap": "954.7205252",
        "Global_GDP%": "0.00010191"
    },
    "129821": {
        "Index": "129821",
        "ID": "86735",
        "Name": "Nikolay Noev",
        "Sex": "M",
        "Age": "24.0",
        "Height": "166.0",
        "Weight": "55.0",
        "Team": "Tajikistan",
        "NOC": "TJK",
        "Games": "2012 Summer",
        "Year": "2012",
        "Season": "Summer",
        "City": "London",
        "Sport": "Wrestling",
        "Event": "Wrestling Men's Featherweight, Freestyle",
        "Medal": "",
        "Host": "0",
        "Nat_Pop": "7995062.0",
        "Global_Pop%": "0.001126477",
        "Rural_Pop%": "73.432",
        "Life_Expect": "70.234",
        "GDP": "7633049792.0",
        "GDP_Per_Cap": "954.7205252",
        "Global_GDP%": "0.00010191"
    },
    "133836": {
        "Index": "133836",
        "ID": "89431",
        "Name": "Sergey Orin",
        "Sex": "M",
        "Age": "17.0",
        "Height": "",
        "Weight": "",
        "Team": "Tajikistan",
        "NOC": "TJK",
        "Games": "1996 Summer",
        "Year": "1996",
        "Season": "Summer",
        "City": "Atlanta",
        "Sport": "Diving",
        "Event": "Diving Men's Springboard",
        "Medal": "",
        "Host": "0",
        "Nat_Pop": "5849540.0",
        "Global_Pop%": "0.001009835",
        "Rural_Pop%": "71.662",
        "Life_Expect": "63.618",
        "GDP": "1043893063.0",
        "GDP_Per_Cap": "178.4572912",
        "Global_GDP%": "3.3e-05"
    },
    "133838": {
        "Index": "133838",
        "ID": "89435",
        "Name": "Farhod Oripov",
        "Sex": "M",
        "Age": "16.0",
        "Height": "166.0",
        "Weight": "65.0",
        "Team": "Tajikistan",
        "NOC": "TJK",
        "Games": "2000 Summer",
        "Year": "2000",
        "Season": "Summer",
        "City": "Sydney",
        "Sport": "Swimming",
        "Event": "Swimming Men's 100 metres Freestyle",
        "Medal": "",
        "Host": "0",
        "Nat_Pop": "6216205.0",
        "Global_Pop%": "0.001016039",
        "Rural_Pop%": "73.514",
        "Life_Expect": "65.485",
        "GDP": "860550305.8",
        "GDP_Per_Cap": "138.4366033",
        "Global_GDP%": "2.56e-05"
    },
    "134933": {
        "Index": "134933",
        "ID": "90155",
        "Name": "Vladislava \"Vlada\" Ovcharenko",
        "Sex": "F",
        "Age": "25.0",
        "Height": "166.0",
        "Weight": "66.0",
        "Team": "Tajikistan",
        "NOC": "TJK",
        "Games": "2012 Summer",
        "Year": "2012",
        "Season": "Summer",
        "City": "London",
        "Sport": "Athletics",
        "Event": "Athletics Women's 200 metres",
        "Medal": "",
        "Host": "0",
        "Nat_Pop": "7995062.0",
        "Global_Pop%": "0.001126477",
        "Rural_Pop%": "73.432",
        "Life_Expect": "70.234",
        "GDP": "7633049792.0",
        "GDP_Per_Cap": "954.7205252",
        "Global_GDP%": "0.00010191"
    },
    "145667": {
        "Index": "145667",
        "ID": "97198",
        "Name": "Kristina Pronzhenko",
        "Sex": "F",
        "Age": "27.0",
        "Height": "172.0",
        "Weight": "60.0",
        "Team": "Tajikistan",
        "NOC": "TJK",
        "Games": "2016 Summer",
        "Year": "2016",
        "Season": "Summer",
        "City": "Rio de Janeiro",
        "Sport": "Athletics",
        "Event": "Athletics Women's 200 metres",
        "Medal": "",
        "Host": "0",
        "Nat_Pop": "8734951.0",
        "Global_Pop%": "0.001173716",
        "Rural_Pop%": "73.109",
        "Life_Expect": "71.051",
        "GDP": "6951657159.0",
        "GDP_Per_Cap": "795.8438644",
        "Global_GDP%": "9.17e-05"
    },
    "146685": {
        "Index": "146685",
        "ID": "97836",
        "Name": "Alisher Qudratov",
        "Sex": "M",
        "Age": "28.0",
        "Height": "160.0",
        "Weight": "65.0",
        "Team": "Tajikistan",
        "NOC": "TJK",
        "Games": "2014 Winter",
        "Year": "2014",
        "Season": "Winter",
        "City": "Sochi",
        "Sport": "Alpine Skiing",
        "Event": "Alpine Skiing Men's Slalom",
        "Medal": "",
        "Host": "0",
        "Nat_Pop": "8362745.0",
        "Global_Pop%": "0.001150469",
        "Rural_Pop%": "73.308",
        "Life_Expect": "70.69",
        "GDP": "9236309138.0",
        "GDP_Per_Cap": "1104.459019",
        "Global_GDP%": "0.000116915"
    },
    "146918": {
        "Index": "146918",
        "ID": "98007",
        "Name": "Jahon Qurbanov",
        "Sex": "M",
        "Age": "22.0",
        "Height": "186.0",
        "Weight": "81.0",
        "Team": "Tajikistan",
        "NOC": "TJK",
        "Games": "2008 Summer",
        "Year": "2008",
        "Season": "Summer",
        "City": "Beijing",
        "Sport": "Boxing",
        "Event": "Boxing Men's Light-Heavyweight",
        "Medal": "",
        "Host": "0",
        "Nat_Pop": "7309728.0",
        "Global_Pop%": "0.001080722",
        "Rural_Pop%": "73.517",
        "Life_Expect": "68.902",
        "GDP": "5161336170.0",
        "GDP_Per_Cap": "706.0914127",
        "Global_GDP%": "8.13e-05"
    },
    "146919": {
        "Index": "146919",
        "ID": "98007",
        "Name": "Jahon Qurbanov",
        "Sex": "M",
        "Age": "26.0",
        "Height": "186.0",
        "Weight": "81.0",
        "Team": "Tajikistan",
        "NOC": "TJK",
        "Games": "2012 Summer",
        "Year": "2012",
        "Season": "Summer",
        "City": "London",
        "Sport": "Boxing",
        "Event": "Boxing Men's Light-Heavyweight",
        "Medal": "",
        "Host": "0",
        "Nat_Pop": "7995062.0",
        "Global_Pop%": "0.001126477",
        "Rural_Pop%": "73.432",
        "Life_Expect": "70.234",
        "GDP": "7633049792.0",
        "GDP_Per_Cap": "954.7205252",
        "Global_GDP%": "0.00010191"
    },
    "147370": {
        "Index": "147370",
        "ID": "98348",
        "Name": "Saidahtam Rahimov",
        "Sex": "M",
        "Age": "23.0",
        "Height": "",
        "Weight": "",
        "Team": "Tajikistan",
        "NOC": "TJK",
        "Games": "1996 Summer",
        "Year": "1996",
        "Season": "Summer",
        "City": "Atlanta",
        "Sport": "Judo",
        "Event": "Judo Men's Heavyweight",
        "Medal": "",
        "Host": "0",
        "Nat_Pop": "5849540.0",
        "Global_Pop%": "0.001009835",
        "Rural_Pop%": "71.662",
        "Life_Expect": "63.618",
        "GDP": "1043893063.0",
        "GDP_Per_Cap": "178.4572912",
        "Global_GDP%": "3.3e-05"
    },
    "158097": {
        "Index": "158097",
        "ID": "105458",
        "Name": "Nizom Sangov",
        "Sex": "M",
        "Age": "25.0",
        "Height": "170.0",
        "Weight": "69.0",
        "Team": "Tajikistan",
        "NOC": "TJK",
        "Games": "2008 Summer",
        "Year": "2008",
        "Season": "Summer",
        "City": "Beijing",
        "Sport": "Weightlifting",
        "Event": "Weightlifting Men's Lightweight",
        "Medal": "",
        "Host": "0",
        "Nat_Pop": "7309728.0",
        "Global_Pop%": "0.001080722",
        "Rural_Pop%": "73.517",
        "Life_Expect": "68.902",
        "GDP": "5161336170.0",
        "GDP_Per_Cap": "706.0914127",
        "Global_GDP%": "8.13e-05"
    },
    "164648": {
        "Index": "164648",
        "ID": "109937",
        "Name": "Nataliya Shlemova",
        "Sex": "F",
        "Age": "18.0",
        "Height": "",
        "Weight": "",
        "Team": "Tajikistan",
        "NOC": "TJK",
        "Games": "1996 Summer",
        "Year": "1996",
        "Season": "Summer",
        "City": "Atlanta",
        "Sport": "Diving",
        "Event": "Diving Women's Springboard",
        "Medal": "",
        "Host": "0",
        "Nat_Pop": "5849540.0",
        "Global_Pop%": "0.001009835",
        "Rural_Pop%": "71.662",
        "Life_Expect": "63.618",
        "GDP": "1043893063.0",
        "GDP_Per_Cap": "178.4572912",
        "Global_GDP%": "3.3e-05"
    },
    "168793": {
        "Index": "168793",
        "ID": "112645",
        "Name": "Parviz Sobirov",
        "Sex": "M",
        "Age": "31.0",
        "Height": "180.0",
        "Weight": "90.0",
        "Team": "Tajikistan",
        "NOC": "TJK",
        "Games": "2012 Summer",
        "Year": "2012",
        "Season": "Summer",
        "City": "London",
        "Sport": "Judo",
        "Event": "Judo Men's Middleweight",
        "Medal": "",
        "Host": "0",
        "Nat_Pop": "7995062.0",
        "Global_Pop%": "0.001126477",
        "Rural_Pop%": "73.432",
        "Life_Expect": "70.234",
        "GDP": "7633049792.0",
        "GDP_Per_Cap": "954.7205252",
        "Global_GDP%": "0.00010191"
    },
    "184747": {
        "Index": "184747",
        "ID": "122997",
        "Name": "Anastasiya Tyurina",
        "Sex": "F",
        "Age": "14.0",
        "Height": "165.0",
        "Weight": "50.0",
        "Team": "Tajikistan",
        "NOC": "TJK",
        "Games": "2016 Summer",
        "Year": "2016",
        "Season": "Summer",
        "City": "Rio de Janeiro",
        "Sport": "Swimming",
        "Event": "Swimming Women's 50 metres Freestyle",
        "Medal": "",
        "Host": "0",
        "Nat_Pop": "8734951.0",
        "Global_Pop%": "0.001173716",
        "Rural_Pop%": "73.109",
        "Life_Expect": "71.051",
        "GDP": "6951657159.0",
        "GDP_Per_Cap": "795.8438644",
        "Global_GDP%": "9.17e-05"
    },
    "185768": {
        "Index": "185768",
        "ID": "123604",
        "Name": "Komronshokh Ustopiriyon",
        "Sex": "M",
        "Age": "23.0",
        "Height": "182.0",
        "Weight": "90.0",
        "Team": "Tajikistan",
        "NOC": "TJK",
        "Games": "2016 Summer",
        "Year": "2016",
        "Season": "Summer",
        "City": "Rio de Janeiro",
        "Sport": "Judo",
        "Event": "Judo Men's Middleweight",
        "Medal": "",
        "Host": "0",
        "Nat_Pop": "8734951.0",
        "Global_Pop%": "0.001173716",
        "Rural_Pop%": "73.109",
        "Life_Expect": "71.051",
        "GDP": "6951657159.0",
        "GDP_Per_Cap": "795.8438644",
        "Global_GDP%": "9.17e-05"
    },
    "200488": {
        "Index": "200488",
        "ID": "133509",
        "Name": "Anvar Yunusov",
        "Sex": "M",
        "Age": "21.0",
        "Height": "170.0",
        "Weight": "55.0",
        "Team": "Tajikistan",
        "NOC": "TJK",
        "Games": "2008 Summer",
        "Year": "2008",
        "Season": "Summer",
        "City": "Beijing",
        "Sport": "Boxing",
        "Event": "Boxing Men's Flyweight",
        "Medal": "",
        "Host": "0",
        "Nat_Pop": "7309728.0",
        "Global_Pop%": "0.001080722",
        "Rural_Pop%": "73.517",
        "Life_Expect": "68.902",
        "GDP": "5161336170.0",
        "GDP_Per_Cap": "706.0914127",
        "Global_GDP%": "8.13e-05"
    },
    "200489": {
        "Index": "200489",
        "ID": "133509",
        "Name": "Anvar Yunusov",
        "Sex": "M",
        "Age": "25.0",
        "Height": "170.0",
        "Weight": "55.0",
        "Team": "Tajikistan",
        "NOC": "TJK",
        "Games": "2012 Summer",
        "Year": "2012",
        "Season": "Summer",
        "City": "London",
        "Sport": "Boxing",
        "Event": "Boxing Men's Bantamweight",
        "Medal": "",
        "Host": "0",
        "Nat_Pop": "7995062.0",
        "Global_Pop%": "0.001126477",
        "Rural_Pop%": "73.432",
        "Life_Expect": "70.234",
        "GDP": "7633049792.0",
        "GDP_Per_Cap": "954.7205252",
        "Global_GDP%": "0.00010191"
    },
    "200490": {
        "Index": "200490",
        "ID": "133509",
        "Name": "Anvar Yunusov",
        "Sex": "M",
        "Age": "29.0",
        "Height": "170.0",
        "Weight": "55.0",
        "Team": "Tajikistan",
        "NOC": "TJK",
        "Games": "2016 Summer",
        "Year": "2016",
        "Season": "Summer",
        "City": "Rio de Janeiro",
        "Sport": "Boxing",
        "Event": "Boxing Men's Lightweight",
        "Medal": "",
        "Host": "0",
        "Nat_Pop": "8734951.0",
        "Global_Pop%": "0.001173716",
        "Rural_Pop%": "73.109",
        "Life_Expect": "71.051",
        "GDP": "6951657159.0",
        "GDP_Per_Cap": "795.8438644",
        "Global_GDP%": "9.17e-05"
    },
    "200571": {
        "Index": "200571",
        "ID": "133557",
        "Name": "Zelimkhon Yusufov",
        "Sex": "M",
        "Age": "28.0",
        "Height": "174.0",
        "Weight": "66.0",
        "Team": "Tajikistan",
        "NOC": "TJK",
        "Games": "2012 Summer",
        "Year": "2012",
        "Season": "Summer",
        "City": "London",
        "Sport": "Wrestling",
        "Event": "Wrestling Men's Welterweight, Freestyle",
        "Medal": "",
        "Host": "0",
        "Nat_Pop": "7995062.0",
        "Global_Pop%": "0.001126477",
        "Rural_Pop%": "73.432",
        "Life_Expect": "70.234",
        "GDP": "7633049792.0",
        "GDP_Per_Cap": "954.7205252",
        "Global_GDP%": "0.00010191"
    },
    "200610": {
        "Index": "200610",
        "ID": "133584",
        "Name": "Sergey Zabavskiy",
        "Sex": "M",
        "Age": "26.0",
        "Height": "178.0",
        "Weight": "60.0",
        "Team": "Tajikistan",
        "NOC": "TJK",
        "Games": "2000 Summer",
        "Year": "2000",
        "Season": "Summer",
        "City": "Sydney",
        "Sport": "Athletics",
        "Event": "Athletics Men's Marathon",
        "Medal": "",
        "Host": "0",
        "Nat_Pop": "6216205.0",
        "Global_Pop%": "0.001016039",
        "Rural_Pop%": "73.514",
        "Life_Expect": "65.485",
        "GDP": "860550305.8",
        "GDP_Per_Cap": "138.4366033",
        "Global_GDP%": "2.56e-05"
    }
}