{
    "Athletics": {
        "Index": "169208",
        "Name": "Jacqueline Mercedes Solz Inturias",
        "Sex": "F",
        "Age": "27.0",
        "Height": "162.0",
        "Weight": "50.0",
        "Team": "Bolivia",
        "NOC": "BOL",
        "Year": "1992",
        "Sport": "Athletics",
        "Medal": "",
        "Host": "0",
        "Nat_Pop": "7131707.0",
        "Global_Pop%": "0.001307097",
        "Rural_Pop%": "42.452",
        "Life_Expect": "56.195",
        "GDP": "5643893347.0",
        "GDP_Per_Cap": "791.3804293",
        "Global_GDP%": "0.000222201"
    },
    "Shooting": {
        "Index": "157642",
        "Name": "Jaime Snchez",
        "Sex": "M",
        "Age": "49.0",
        "Height": "172.0",
        "Weight": "75.0",
        "Team": "Bolivia",
        "NOC": "BOL",
        "Year": "1976",
        "Sport": "Shooting",
        "Medal": "",
        "Host": "0",
        "Nat_Pop": "5119833.0",
        "Global_Pop%": "0.001236928",
        "Rural_Pop%": "58.376",
        "Life_Expect": "48.183",
        "GDP": "2732083958.0",
        "GDP_Per_Cap": "533.6275535",
        "Global_GDP%": "0.000425558"
    },
    "Cycling": {
        "Index": "185932",
        "Name": "Pedro Antonio Vaca Montero",
        "Sex": "M",
        "Age": "31.0",
        "Height": "174.0",
        "Weight": "72.0",
        "Team": "Bolivia",
        "NOC": "BOL",
        "Year": "1992",
        "Sport": "Cycling",
        "Medal": "",
        "Host": "0",
        "Nat_Pop": "7131707.0",
        "Global_Pop%": "0.001307097",
        "Rural_Pop%": "42.452",
        "Life_Expect": "56.195",
        "GDP": "5643893347.0",
        "GDP_Per_Cap": "791.3804293",
        "Global_GDP%": "0.000222201"
    },
    "Judo": {
        "Index": "138394",
        "Name": "Juan Jos Paz",
        "Sex": "M",
        "Age": "23.0",
        "Height": "168.0",
        "Weight": "66.0",
        "Team": "Bolivia",
        "NOC": "BOL",
        "Year": "2004",
        "Sport": "Judo",
        "Medal": "",
        "Host": "0",
        "Nat_Pop": "8967741.0",
        "Global_Pop%": "0.001393297",
        "Rural_Pop%": "36.268",
        "Life_Expect": "62.968",
        "GDP": "8773451739.0",
        "GDP_Per_Cap": "978.3346485",
        "Global_GDP%": "0.000200307"
    },
    "Fencing": {
        "Index": "151939",
        "Name": "Miguel Robles",
        "Sex": "M",
        "Age": "21.0",
        "Height": "",
        "Weight": "",
        "Team": "Bolivia",
        "NOC": "BOL",
        "Year": "1996",
        "Sport": "Fencing",
        "Medal": "",
        "Host": "0",
        "Nat_Pop": "7717443.0",
        "Global_Pop%": "0.001332301",
        "Rural_Pop%": "40.109",
        "Life_Expect": "58.423",
        "GDP": "7396966657.0",
        "GDP_Per_Cap": "958.4737661",
        "Global_GDP%": "0.000234081"
    },
    "Tennis": {
        "Index": "25595",
        "Name": "Diego Camacho",
        "Sex": "M",
        "Age": "17.0",
        "Height": "182.0",
        "Weight": "",
        "Team": "Bolivia",
        "NOC": "BOL",
        "Year": "2000",
        "Sport": "Tennis",
        "Medal": "",
        "Host": "0",
        "Nat_Pop": "8339512.0",
        "Global_Pop%": "0.001363094",
        "Rural_Pop%": "38.166",
        "Life_Expect": "60.69",
        "GDP": "8397912509.0",
        "GDP_Per_Cap": "1007.002869",
        "Global_GDP%": "0.000249938"
    },
    "Wrestling": {
        "Index": "25604",
        "Name": "Leonardo Camacho",
        "Sex": "M",
        "Age": "27.0",
        "Height": "170.0",
        "Weight": "68.0",
        "Team": "Bolivia",
        "NOC": "BOL",
        "Year": "1984",
        "Sport": "Wrestling",
        "Medal": "",
        "Host": "0",
        "Nat_Pop": "6085496.0",
        "Global_Pop%": "0.00127847",
        "Rural_Pop%": "50.496",
        "Life_Expect": "51.965",
        "GDP": "6169481549.0",
        "GDP_Per_Cap": "1013.800937",
        "Global_GDP%": "0.000509875"
    },
    "Boxing": {
        "Index": "28169",
        "Name": "Ren Centellas",
        "Sex": "M",
        "Age": "24.0",
        "Height": "155.0",
        "Weight": "48.0",
        "Team": "Bolivia",
        "NOC": "BOL",
        "Year": "1984",
        "Sport": "Boxing",
        "Medal": "",
        "Host": "0",
        "Nat_Pop": "6085496.0",
        "Global_Pop%": "0.00127847",
        "Rural_Pop%": "50.496",
        "Life_Expect": "51.965",
        "GDP": "6169481549.0",
        "GDP_Per_Cap": "1013.800937",
        "Global_GDP%": "0.000509875"
    },
    "Weightlifting": {
        "Index": "178605",
        "Name": "Casiano Tejeda Arce",
        "Sex": "M",
        "Age": "20.0",
        "Height": "",
        "Weight": "89.0",
        "Team": "Bolivia",
        "NOC": "BOL",
        "Year": "1992",
        "Sport": "Weightlifting",
        "Medal": "",
        "Host": "0",
        "Nat_Pop": "7131707.0",
        "Global_Pop%": "0.001307097",
        "Rural_Pop%": "42.452",
        "Life_Expect": "56.195",
        "GDP": "5643893347.0",
        "GDP_Per_Cap": "791.3804293",
        "Global_GDP%": "0.000222201"
    },
    "Gymnastics": {
        "Index": "38193",
        "Name": "Maria Jos de la Fuente",
        "Sex": "F",
        "Age": "15.0",
        "Height": "150.0",
        "Weight": "40.0",
        "Team": "Bolivia",
        "NOC": "BOL",
        "Year": "2004",
        "Sport": "Gymnastics",
        "Medal": "",
        "Host": "0",
        "Nat_Pop": "8967741.0",
        "Global_Pop%": "0.001393297",
        "Rural_Pop%": "36.268",
        "Life_Expect": "62.968",
        "GDP": "8773451739.0",
        "GDP_Per_Cap": "978.3346485",
        "Global_GDP%": "0.000200307"
    },
    "Swimming": {
        "Index": "182095",
        "Name": "Karen Milenka Torrez Guzman",
        "Sex": "F",
        "Age": "24.0",
        "Height": "165.0",
        "Weight": "58.0",
        "Team": "Bolivia",
        "NOC": "BOL",
        "Year": "2016",
        "Sport": "Swimming",
        "Medal": "",
        "Host": "0",
        "Nat_Pop": "10887882.0",
        "Global_Pop%": "0.001463005",
        "Rural_Pop%": "31.089",
        "Life_Expect": "69.125",
        "GDP": "33806395514.0",
        "GDP_Per_Cap": "3104.956089",
        "Global_GDP%": "0.000445995"
    },
    "Diving": {
        "Index": "75846",
        "Name": "Tony Iglesias",
        "Sex": "M",
        "Age": "23.0",
        "Height": "",
        "Weight": "",
        "Team": "Bolivia",
        "NOC": "BOL",
        "Year": "1996",
        "Sport": "Diving",
        "Medal": "",
        "Host": "0",
        "Nat_Pop": "7717443.0",
        "Global_Pop%": "0.001332301",
        "Rural_Pop%": "40.109",
        "Life_Expect": "58.423",
        "GDP": "7396966657.0",
        "GDP_Per_Cap": "958.4737661",
        "Global_GDP%": "0.000234081"
    },
    "Canoeing": {
        "Index": "76534",
        "Name": "Fernando Inchauste Montalvo",
        "Sex": "M",
        "Age": "38.0",
        "Height": "184.0",
        "Weight": "85.0",
        "Team": "Bolivia",
        "NOC": "BOL",
        "Year": "1968",
        "Sport": "Canoeing",
        "Medal": "",
        "Host": "0",
        "Nat_Pop": "4324064.0",
        "Global_Pop%": "0.001223277",
        "Rural_Pop%": "60.834",
        "Life_Expect": "44.898",
        "GDP": "908874537.0",
        "GDP_Per_Cap": "210.1898901",
        "Global_GDP%": "0.00037249"
    },
    "Equestrianism": {
        "Index": "128773",
        "Name": "Roberto Maria Nielsen-Reyes Kurschner",
        "Sex": "M",
        "Age": "33.0",
        "Height": "176.0",
        "Weight": "64.0",
        "Team": "Bolivia",
        "NOC": "BOL",
        "Year": "1976",
        "Sport": "Equestrianism",
        "Medal": "",
        "Host": "0",
        "Nat_Pop": "5119833.0",
        "Global_Pop%": "0.001236928",
        "Rural_Pop%": "58.376",
        "Life_Expect": "48.183",
        "GDP": "2732083958.0",
        "GDP_Per_Cap": "533.6275535",
        "Global_GDP%": "0.000425558"
    }
}