{
    "7941": {
        "Index": "7941",
        "ID": "5534",
        "Name": "Melissa Ashby",
        "Sex": "F",
        "Age": "18.0",
        "Height": "168.0",
        "Weight": "64.0",
        "Team": "Grenada",
        "NOC": "GRD",
        "Games": "2004 Summer",
        "Year": "2004",
        "Season": "Summer",
        "City": "Athina",
        "Sport": "Swimming",
        "Event": "Swimming Women's 100 metres Breaststroke",
        "Medal": "",
        "Host": "0",
        "Nat_Pop": "102656.0",
        "Global_Pop%": "1.59e-05",
        "Rural_Pop%": "64.037",
        "Life_Expect": "71.213",
        "GDP": "599118592.6",
        "GDP_Per_Cap": "5836.177063",
        "Global_GDP%": "1.37e-05"
    },
    "11948": {
        "Index": "11948",
        "ID": "8281",
        "Name": "Jacinta Bartholomew",
        "Sex": "F",
        "Age": "19.0",
        "Height": "175.0",
        "Weight": "54.0",
        "Team": "Grenada",
        "NOC": "GRD",
        "Games": "1984 Summer",
        "Year": "1984",
        "Season": "Summer",
        "City": "Los Angeles",
        "Sport": "Athletics",
        "Event": "Athletics Women's Long Jump",
        "Medal": "",
        "Host": "0",
        "Nat_Pop": "98439.0",
        "Global_Pop%": "2.07e-05",
        "Rural_Pop%": "66.865",
        "Life_Expect": "67.449",
        "GDP": "145533296.3",
        "GDP_Per_Cap": "1478.410958",
        "Global_GDP%": "1.2e-05"
    },
    "11949": {
        "Index": "11949",
        "ID": "8283",
        "Name": "Trish Bartholomew",
        "Sex": "F",
        "Age": "21.0",
        "Height": "160.0",
        "Weight": "59.0",
        "Team": "Grenada",
        "NOC": "GRD",
        "Games": "2008 Summer",
        "Year": "2008",
        "Season": "Summer",
        "City": "Beijing",
        "Sport": "Athletics",
        "Event": "Athletics Women's 400 metres",
        "Medal": "",
        "Host": "0",
        "Nat_Pop": "103930.0",
        "Global_Pop%": "1.54e-05",
        "Rural_Pop%": "64.225",
        "Life_Expect": "72.142",
        "GDP": "825977888.9",
        "GDP_Per_Cap": "7947.444327",
        "Global_GDP%": "1.3e-05"
    },
    "15704": {
        "Index": "15704",
        "ID": "10703",
        "Name": "Neisha Bernard-Thomas",
        "Sex": "F",
        "Age": "27.0",
        "Height": "165.0",
        "Weight": "56.0",
        "Team": "Grenada",
        "NOC": "GRD",
        "Games": "2008 Summer",
        "Year": "2008",
        "Season": "Summer",
        "City": "Beijing",
        "Sport": "Athletics",
        "Event": "Athletics Women's 800 metres",
        "Medal": "",
        "Host": "0",
        "Nat_Pop": "103930.0",
        "Global_Pop%": "1.54e-05",
        "Rural_Pop%": "64.225",
        "Life_Expect": "72.142",
        "GDP": "825977888.9",
        "GDP_Per_Cap": "7947.444327",
        "Global_GDP%": "1.3e-05"
    },
    "15705": {
        "Index": "15705",
        "ID": "10703",
        "Name": "Neisha Bernard-Thomas",
        "Sex": "F",
        "Age": "31.0",
        "Height": "165.0",
        "Weight": "56.0",
        "Team": "Grenada",
        "NOC": "GRD",
        "Games": "2012 Summer",
        "Year": "2012",
        "Season": "Summer",
        "City": "London",
        "Sport": "Athletics",
        "Event": "Athletics Women's 800 metres",
        "Medal": "",
        "Host": "0",
        "Nat_Pop": "105481.0",
        "Global_Pop%": "1.49e-05",
        "Rural_Pop%": "64.399",
        "Life_Expect": "73.044",
        "GDP": "799882148.1",
        "GDP_Per_Cap": "7583.187001",
        "Global_GDP%": "1.07e-05"
    },
    "22197": {
        "Index": "22197",
        "ID": "15191",
        "Name": "Richard Britton",
        "Sex": "M",
        "Age": "19.0",
        "Height": "",
        "Weight": "",
        "Team": "Grenada",
        "NOC": "GRD",
        "Games": "1996 Summer",
        "Year": "1996",
        "Season": "Summer",
        "City": "Atlanta",
        "Sport": "Athletics",
        "Event": "Athletics Men's 4 x 400 metres Relay",
        "Medal": "",
        "Host": "0",
        "Nat_Pop": "100796.0",
        "Global_Pop%": "1.74e-05",
        "Rural_Pop%": "65.189",
        "Life_Expect": "69.57",
        "GDP": "366911444.4",
        "GDP_Per_Cap": "3640.138938",
        "Global_GDP%": "1.16e-05"
    },
    "29901": {
        "Index": "29901",
        "ID": "20422",
        "Name": "Oreoluwa Cherebin",
        "Sex": "F",
        "Age": "18.0",
        "Height": "150.0",
        "Weight": "54.0",
        "Team": "Grenada",
        "NOC": "GRD",
        "Games": "2016 Summer",
        "Year": "2016",
        "Season": "Summer",
        "City": "Rio de Janeiro",
        "Sport": "Swimming",
        "Event": "Swimming Women's 100 metres Butterfly",
        "Medal": "",
        "Host": "0",
        "Nat_Pop": "107317.0",
        "Global_Pop%": "1.44e-05",
        "Rural_Pop%": "64.384",
        "Life_Expect": "73.659",
        "GDP": "1056188593.0",
        "GDP_Per_Cap": "9841.764054",
        "Global_GDP%": "1.39e-05"
    },
    "32805": {
        "Index": "32805",
        "ID": "22455",
        "Name": "Christopher \"Chris\" Collins",
        "Sex": "M",
        "Age": "24.0",
        "Height": "178.0",
        "Weight": "81.0",
        "Team": "Grenada",
        "NOC": "GRD",
        "Games": "1984 Summer",
        "Year": "1984",
        "Season": "Summer",
        "City": "Los Angeles",
        "Sport": "Boxing",
        "Event": "Boxing Men's Middleweight",
        "Medal": "",
        "Host": "0",
        "Nat_Pop": "98439.0",
        "Global_Pop%": "2.07e-05",
        "Rural_Pop%": "66.865",
        "Life_Expect": "67.449",
        "GDP": "145533296.3",
        "GDP_Per_Cap": "1478.410958",
        "Global_GDP%": "1.2e-05"
    },
    "32806": {
        "Index": "32806",
        "ID": "22455",
        "Name": "Christopher \"Chris\" Collins",
        "Sex": "M",
        "Age": "28.0",
        "Height": "178.0",
        "Weight": "81.0",
        "Team": "Grenada",
        "NOC": "GRD",
        "Games": "1988 Summer",
        "Year": "1988",
        "Season": "Summer",
        "City": "Seoul",
        "Sport": "Boxing",
        "Event": "Boxing Men's Light-Heavyweight",
        "Medal": "",
        "Host": "0",
        "Nat_Pop": "98062.0",
        "Global_Pop%": "1.92e-05",
        "Rural_Pop%": "66.67",
        "Life_Expect": "68.247",
        "GDP": "236357518.5",
        "GDP_Per_Cap": "2410.286538",
        "Global_GDP%": "1.24e-05"
    },
    "50254": {
        "Index": "50254",
        "ID": "34554",
        "Name": "Delon Felix",
        "Sex": "M",
        "Age": "18.0",
        "Height": "",
        "Weight": "",
        "Team": "Grenada",
        "NOC": "GRD",
        "Games": "1992 Summer",
        "Year": "1992",
        "Season": "Summer",
        "City": "Barcelona",
        "Sport": "Athletics",
        "Event": "Athletics Men's 400 metres",
        "Medal": "",
        "Host": "0",
        "Nat_Pop": "97198.0",
        "Global_Pop%": "1.78e-05",
        "Rural_Pop%": "66.235",
        "Life_Expect": "68.925",
        "GDP": "310160444.4",
        "GDP_Per_Cap": "3191.016733",
        "Global_GDP%": "1.22e-05"
    },
    "50257": {
        "Index": "50257",
        "ID": "34556",
        "Name": "Garth Felix",
        "Sex": "M",
        "Age": "21.0",
        "Height": "175.0",
        "Weight": "70.0",
        "Team": "Grenada",
        "NOC": "GRD",
        "Games": "1988 Summer",
        "Year": "1988",
        "Season": "Summer",
        "City": "Seoul",
        "Sport": "Boxing",
        "Event": "Boxing Men's Light-Middleweight",
        "Medal": "",
        "Host": "0",
        "Nat_Pop": "98062.0",
        "Global_Pop%": "1.92e-05",
        "Rural_Pop%": "66.67",
        "Life_Expect": "68.247",
        "GDP": "236357518.5",
        "GDP_Per_Cap": "2410.286538",
        "Global_GDP%": "1.24e-05"
    },
    "50261": {
        "Index": "50261",
        "ID": "34559",
        "Name": "Kurt Anthony Felix",
        "Sex": "M",
        "Age": "24.0",
        "Height": "182.0",
        "Weight": "76.0",
        "Team": "Grenada",
        "NOC": "GRD",
        "Games": "2012 Summer",
        "Year": "2012",
        "Season": "Summer",
        "City": "London",
        "Sport": "Athletics",
        "Event": "Athletics Men's Decathlon",
        "Medal": "",
        "Host": "0",
        "Nat_Pop": "105481.0",
        "Global_Pop%": "1.49e-05",
        "Rural_Pop%": "64.399",
        "Life_Expect": "73.044",
        "GDP": "799882148.1",
        "GDP_Per_Cap": "7583.187001",
        "Global_GDP%": "1.07e-05"
    },
    "50262": {
        "Index": "50262",
        "ID": "34559",
        "Name": "Kurt Anthony Felix",
        "Sex": "M",
        "Age": "28.0",
        "Height": "182.0",
        "Weight": "76.0",
        "Team": "Grenada",
        "NOC": "GRD",
        "Games": "2016 Summer",
        "Year": "2016",
        "Season": "Summer",
        "City": "Rio de Janeiro",
        "Sport": "Athletics",
        "Event": "Athletics Men's Decathlon",
        "Medal": "",
        "Host": "0",
        "Nat_Pop": "107317.0",
        "Global_Pop%": "1.44e-05",
        "Rural_Pop%": "64.384",
        "Life_Expect": "73.659",
        "GDP": "1056188593.0",
        "GDP_Per_Cap": "9841.764054",
        "Global_GDP%": "1.39e-05"
    },
    "52280": {
        "Index": "52280",
        "ID": "35821",
        "Name": "Sherry Ingrid Veronica Fletcher",
        "Sex": "F",
        "Age": "22.0",
        "Height": "167.0",
        "Weight": "57.0",
        "Team": "Grenada",
        "NOC": "GRD",
        "Games": "2008 Summer",
        "Year": "2008",
        "Season": "Summer",
        "City": "Beijing",
        "Sport": "Athletics",
        "Event": "Athletics Women's 100 metres",
        "Medal": "",
        "Host": "0",
        "Nat_Pop": "103930.0",
        "Global_Pop%": "1.54e-05",
        "Rural_Pop%": "64.225",
        "Life_Expect": "72.142",
        "GDP": "825977888.9",
        "GDP_Per_Cap": "7947.444327",
        "Global_GDP%": "1.3e-05"
    },
    "53569": {
        "Index": "53569",
        "ID": "36656",
        "Name": "Alleyne Jeremy Francique",
        "Sex": "M",
        "Age": "20.0",
        "Height": "188.0",
        "Weight": "75.0",
        "Team": "Grenada",
        "NOC": "GRD",
        "Games": "1996 Summer",
        "Year": "1996",
        "Season": "Summer",
        "City": "Atlanta",
        "Sport": "Athletics",
        "Event": "Athletics Men's 4 x 400 metres Relay",
        "Medal": "",
        "Host": "0",
        "Nat_Pop": "100796.0",
        "Global_Pop%": "1.74e-05",
        "Rural_Pop%": "65.189",
        "Life_Expect": "69.57",
        "GDP": "366911444.4",
        "GDP_Per_Cap": "3640.138938",
        "Global_GDP%": "1.16e-05"
    },
    "53570": {
        "Index": "53570",
        "ID": "36656",
        "Name": "Alleyne Jeremy Francique",
        "Sex": "M",
        "Age": "28.0",
        "Height": "188.0",
        "Weight": "75.0",
        "Team": "Grenada",
        "NOC": "GRD",
        "Games": "2004 Summer",
        "Year": "2004",
        "Season": "Summer",
        "City": "Athina",
        "Sport": "Athletics",
        "Event": "Athletics Men's 400 metres",
        "Medal": "",
        "Host": "0",
        "Nat_Pop": "102656.0",
        "Global_Pop%": "1.59e-05",
        "Rural_Pop%": "64.037",
        "Life_Expect": "71.213",
        "GDP": "599118592.6",
        "GDP_Per_Cap": "5836.177063",
        "Global_GDP%": "1.37e-05"
    },
    "53571": {
        "Index": "53571",
        "ID": "36656",
        "Name": "Alleyne Jeremy Francique",
        "Sex": "M",
        "Age": "32.0",
        "Height": "188.0",
        "Weight": "75.0",
        "Team": "Grenada",
        "NOC": "GRD",
        "Games": "2008 Summer",
        "Year": "2008",
        "Season": "Summer",
        "City": "Beijing",
        "Sport": "Athletics",
        "Event": "Athletics Men's 400 metres",
        "Medal": "",
        "Host": "0",
        "Nat_Pop": "103930.0",
        "Global_Pop%": "1.54e-05",
        "Rural_Pop%": "64.225",
        "Life_Expect": "72.142",
        "GDP": "825977888.9",
        "GDP_Per_Cap": "7947.444327",
        "Global_GDP%": "1.3e-05"
    },
    "57987": {
        "Index": "57987",
        "ID": "39541",
        "Name": "Alison Magdalene George",
        "Sex": "F",
        "Age": "20.0",
        "Height": "",
        "Weight": "",
        "Team": "Grenada",
        "NOC": "GRD",
        "Games": "2008 Summer",
        "Year": "2008",
        "Season": "Summer",
        "City": "Beijing",
        "Sport": "Athletics",
        "Event": "Athletics Women's 200 metres",
        "Medal": "",
        "Host": "0",
        "Nat_Pop": "103930.0",
        "Global_Pop%": "1.54e-05",
        "Rural_Pop%": "64.225",
        "Life_Expect": "72.142",
        "GDP": "825977888.9",
        "GDP_Per_Cap": "7947.444327",
        "Global_GDP%": "1.3e-05"
    },
    "62874": {
        "Index": "62874",
        "ID": "42862",
        "Name": "Agnes Geraldine Griffith",
        "Sex": "F",
        "Age": "19.0",
        "Height": "162.0",
        "Weight": "54.0",
        "Team": "Grenada",
        "NOC": "GRD",
        "Games": "1988 Summer",
        "Year": "1988",
        "Season": "Summer",
        "City": "Seoul",
        "Sport": "Athletics",
        "Event": "Athletics Women's 200 metres",
        "Medal": "",
        "Host": "0",
        "Nat_Pop": "98062.0",
        "Global_Pop%": "1.92e-05",
        "Rural_Pop%": "66.67",
        "Life_Expect": "68.247",
        "GDP": "236357518.5",
        "GDP_Per_Cap": "2410.286538",
        "Global_GDP%": "1.24e-05"
    },
    "62875": {
        "Index": "62875",
        "ID": "42862",
        "Name": "Agnes Geraldine Griffith",
        "Sex": "F",
        "Age": "19.0",
        "Height": "162.0",
        "Weight": "54.0",
        "Team": "Grenada",
        "NOC": "GRD",
        "Games": "1988 Summer",
        "Year": "1988",
        "Season": "Summer",
        "City": "Seoul",
        "Sport": "Athletics",
        "Event": "Athletics Women's 400 metres",
        "Medal": "",
        "Host": "0",
        "Nat_Pop": "98062.0",
        "Global_Pop%": "1.92e-05",
        "Rural_Pop%": "66.67",
        "Life_Expect": "68.247",
        "GDP": "236357518.5",
        "GDP_Per_Cap": "2410.286538",
        "Global_GDP%": "1.24e-05"
    },
    "74653": {
        "Index": "74653",
        "ID": "50882",
        "Name": "Omar Hughes",
        "Sex": "M",
        "Age": "18.0",
        "Height": "",
        "Weight": "",
        "Team": "Grenada",
        "NOC": "GRD",
        "Games": "2000 Summer",
        "Year": "2000",
        "Season": "Summer",
        "City": "Sydney",
        "Sport": "Swimming",
        "Event": "Swimming Men's 50 metres Freestyle",
        "Medal": "",
        "Host": "0",
        "Nat_Pop": "101619.0",
        "Global_Pop%": "1.66e-05",
        "Rural_Pop%": "64.129",
        "Life_Expect": "70.337",
        "GDP": "520044370.4",
        "GDP_Per_Cap": "5117.589923",
        "Global_GDP%": "1.55e-05"
    },
    "78730": {
        "Index": "78730",
        "ID": "53492",
        "Name": "Kirani James",
        "Sex": "M",
        "Age": "19.0",
        "Height": "180.0",
        "Weight": "66.0",
        "Team": "Grenada",
        "NOC": "GRD",
        "Games": "2012 Summer",
        "Year": "2012",
        "Season": "Summer",
        "City": "London",
        "Sport": "Athletics",
        "Event": "Athletics Men's 400 metres",
        "Medal": "Gold",
        "Host": "0",
        "Nat_Pop": "105481.0",
        "Global_Pop%": "1.49e-05",
        "Rural_Pop%": "64.399",
        "Life_Expect": "73.044",
        "GDP": "799882148.1",
        "GDP_Per_Cap": "7583.187001",
        "Global_GDP%": "1.07e-05"
    },
    "78731": {
        "Index": "78731",
        "ID": "53492",
        "Name": "Kirani James",
        "Sex": "M",
        "Age": "23.0",
        "Height": "180.0",
        "Weight": "66.0",
        "Team": "Grenada",
        "NOC": "GRD",
        "Games": "2016 Summer",
        "Year": "2016",
        "Season": "Summer",
        "City": "Rio de Janeiro",
        "Sport": "Athletics",
        "Event": "Athletics Men's 400 metres",
        "Medal": "Silver",
        "Host": "0",
        "Nat_Pop": "107317.0",
        "Global_Pop%": "1.44e-05",
        "Rural_Pop%": "64.384",
        "Life_Expect": "73.659",
        "GDP": "1056188593.0",
        "GDP_Per_Cap": "9841.764054",
        "Global_GDP%": "1.39e-05"
    },
    "81995": {
        "Index": "81995",
        "ID": "55727",
        "Name": "Nigel Rufus Jones",
        "Sex": "M",
        "Age": "20.0",
        "Height": "178.0",
        "Weight": "75.0",
        "Team": "Grenada",
        "NOC": "GRD",
        "Games": "1996 Summer",
        "Year": "1996",
        "Season": "Summer",
        "City": "Atlanta",
        "Sport": "Athletics",
        "Event": "Athletics Men's 4 x 400 metres Relay",
        "Medal": "",
        "Host": "0",
        "Nat_Pop": "100796.0",
        "Global_Pop%": "1.74e-05",
        "Rural_Pop%": "65.189",
        "Life_Expect": "69.57",
        "GDP": "366911444.4",
        "GDP_Per_Cap": "3640.138938",
        "Global_GDP%": "1.16e-05"
    },
    "82340": {
        "Index": "82340",
        "ID": "55970",
        "Name": "Taddeus \"Tad\" Joseph",
        "Sex": "M",
        "Age": "25.0",
        "Height": "157.0",
        "Weight": "53.0",
        "Team": "Grenada",
        "NOC": "GRD",
        "Games": "1988 Summer",
        "Year": "1988",
        "Season": "Summer",
        "City": "Seoul",
        "Sport": "Boxing",
        "Event": "Boxing Men's Bantamweight",
        "Medal": "",
        "Host": "0",
        "Nat_Pop": "98062.0",
        "Global_Pop%": "1.92e-05",
        "Rural_Pop%": "66.67",
        "Life_Expect": "68.247",
        "GDP": "236357518.5",
        "GDP_Per_Cap": "2410.286538",
        "Global_GDP%": "1.24e-05"
    },
    "103162": {
        "Index": "103162",
        "ID": "69238",
        "Name": "Errol \"Kenny\" Lewis",
        "Sex": "M",
        "Age": "22.0",
        "Height": "",
        "Weight": "",
        "Team": "Grenada",
        "NOC": "GRD",
        "Games": "1996 Summer",
        "Year": "1996",
        "Season": "Summer",
        "City": "Atlanta",
        "Sport": "Athletics",
        "Event": "Athletics Men's Long Jump",
        "Medal": "",
        "Host": "0",
        "Nat_Pop": "100796.0",
        "Global_Pop%": "1.74e-05",
        "Rural_Pop%": "65.189",
        "Life_Expect": "69.57",
        "GDP": "366911444.4",
        "GDP_Per_Cap": "3640.138938",
        "Global_GDP%": "1.16e-05"
    },
    "103179": {
        "Index": "103179",
        "ID": "69252",
        "Name": "Randy Benedict Lewis",
        "Sex": "M",
        "Age": "25.0",
        "Height": "188.0",
        "Weight": "74.0",
        "Team": "Grenada",
        "NOC": "GRD",
        "Games": "2004 Summer",
        "Year": "2004",
        "Season": "Summer",
        "City": "Athina",
        "Sport": "Athletics",
        "Event": "Athletics Men's Triple Jump",
        "Medal": "",
        "Host": "0",
        "Nat_Pop": "102656.0",
        "Global_Pop%": "1.59e-05",
        "Rural_Pop%": "64.037",
        "Life_Expect": "71.213",
        "GDP": "599118592.6",
        "GDP_Per_Cap": "5836.177063",
        "Global_GDP%": "1.37e-05"
    },
    "103180": {
        "Index": "103180",
        "ID": "69252",
        "Name": "Randy Benedict Lewis",
        "Sex": "M",
        "Age": "29.0",
        "Height": "188.0",
        "Weight": "74.0",
        "Team": "Grenada",
        "NOC": "GRD",
        "Games": "2008 Summer",
        "Year": "2008",
        "Season": "Summer",
        "City": "Beijing",
        "Sport": "Athletics",
        "Event": "Athletics Men's Triple Jump",
        "Medal": "",
        "Host": "0",
        "Nat_Pop": "103930.0",
        "Global_Pop%": "1.54e-05",
        "Rural_Pop%": "64.225",
        "Life_Expect": "72.142",
        "GDP": "825977888.9",
        "GDP_Per_Cap": "7947.444327",
        "Global_GDP%": "1.3e-05"
    },
    "104044": {
        "Index": "104044",
        "ID": "69688",
        "Name": "Eugene Licorish",
        "Sex": "M",
        "Age": "27.0",
        "Height": "",
        "Weight": "",
        "Team": "Grenada",
        "NOC": "GRD",
        "Games": "1992 Summer",
        "Year": "1992",
        "Season": "Summer",
        "City": "Barcelona",
        "Sport": "Athletics",
        "Event": "Athletics Men's Long Jump",
        "Medal": "",
        "Host": "0",
        "Nat_Pop": "97198.0",
        "Global_Pop%": "1.78e-05",
        "Rural_Pop%": "66.235",
        "Life_Expect": "68.925",
        "GDP": "310160444.4",
        "GDP_Per_Cap": "3191.016733",
        "Global_GDP%": "1.22e-05"
    },
    "106436": {
        "Index": "106436",
        "ID": "71221",
        "Name": "Anthony Longdon",
        "Sex": "M",
        "Age": "",
        "Height": "",
        "Weight": "",
        "Team": "Grenada",
        "NOC": "GRD",
        "Games": "1984 Summer",
        "Year": "1984",
        "Season": "Summer",
        "City": "Los Angeles",
        "Sport": "Boxing",
        "Event": "Boxing Men's Light-Heavyweight",
        "Medal": "",
        "Host": "0",
        "Nat_Pop": "98439.0",
        "Global_Pop%": "2.07e-05",
        "Rural_Pop%": "66.865",
        "Life_Expect": "67.449",
        "GDP": "145533296.3",
        "GDP_Per_Cap": "1478.410958",
        "Global_GDP%": "1.2e-05"
    },
    "123204": {
        "Index": "123204",
        "ID": "82419",
        "Name": "Rolande Moses",
        "Sex": "M",
        "Age": "27.0",
        "Height": "180.0",
        "Weight": "69.0",
        "Team": "Grenada",
        "NOC": "GRD",
        "Games": "2008 Summer",
        "Year": "2008",
        "Season": "Summer",
        "City": "Beijing",
        "Sport": "Boxing",
        "Event": "Boxing Men's Welterweight",
        "Medal": "",
        "Host": "0",
        "Nat_Pop": "103930.0",
        "Global_Pop%": "1.54e-05",
        "Rural_Pop%": "64.225",
        "Life_Expect": "72.142",
        "GDP": "825977888.9",
        "GDP_Per_Cap": "7947.444327",
        "Global_GDP%": "1.3e-05"
    },
    "132865": {
        "Index": "132865",
        "ID": "88821",
        "Name": "Corey Ollivierre",
        "Sex": "M",
        "Age": "19.0",
        "Height": "",
        "Weight": "",
        "Team": "Grenada",
        "NOC": "GRD",
        "Games": "2016 Summer",
        "Year": "2016",
        "Season": "Summer",
        "City": "Rio de Janeiro",
        "Sport": "Swimming",
        "Event": "Swimming Men's 100 metres Breaststroke",
        "Medal": "",
        "Host": "0",
        "Nat_Pop": "107317.0",
        "Global_Pop%": "1.44e-05",
        "Rural_Pop%": "64.384",
        "Life_Expect": "73.659",
        "GDP": "1056188593.0",
        "GDP_Per_Cap": "9841.764054",
        "Global_GDP%": "1.39e-05"
    },
    "141369": {
        "Index": "141369",
        "ID": "94450",
        "Name": "Emrol Phillip",
        "Sex": "M",
        "Age": "18.0",
        "Height": "",
        "Weight": "",
        "Team": "Grenada",
        "NOC": "GRD",
        "Games": "1984 Summer",
        "Year": "1984",
        "Season": "Summer",
        "City": "Los Angeles",
        "Sport": "Boxing",
        "Event": "Boxing Men's Lightweight",
        "Medal": "",
        "Host": "0",
        "Nat_Pop": "98439.0",
        "Global_Pop%": "2.07e-05",
        "Rural_Pop%": "66.865",
        "Life_Expect": "67.449",
        "GDP": "145533296.3",
        "GDP_Per_Cap": "1478.410958",
        "Global_GDP%": "1.2e-05"
    },
    "141371": {
        "Index": "141371",
        "ID": "94452",
        "Name": "Joel Japheth Phillip",
        "Sex": "M",
        "Age": "20.0",
        "Height": "188.0",
        "Weight": "75.0",
        "Team": "Grenada",
        "NOC": "GRD",
        "Games": "2008 Summer",
        "Year": "2008",
        "Season": "Summer",
        "City": "Beijing",
        "Sport": "Athletics",
        "Event": "Athletics Men's 400 metres",
        "Medal": "",
        "Host": "0",
        "Nat_Pop": "103930.0",
        "Global_Pop%": "1.54e-05",
        "Rural_Pop%": "64.225",
        "Life_Expect": "72.142",
        "GDP": "825977888.9",
        "GDP_Per_Cap": "7947.444327",
        "Global_GDP%": "1.3e-05"
    },
    "149031": {
        "Index": "149031",
        "ID": "99474",
        "Name": "Janelle Redhead",
        "Sex": "F",
        "Age": "22.0",
        "Height": "162.0",
        "Weight": "56.0",
        "Team": "Grenada",
        "NOC": "GRD",
        "Games": "2012 Summer",
        "Year": "2012",
        "Season": "Summer",
        "City": "London",
        "Sport": "Athletics",
        "Event": "Athletics Women's 200 metres",
        "Medal": "",
        "Host": "0",
        "Nat_Pop": "105481.0",
        "Global_Pop%": "1.49e-05",
        "Rural_Pop%": "64.399",
        "Life_Expect": "73.044",
        "GDP": "799882148.1",
        "GDP_Per_Cap": "7583.187001",
        "Global_GDP%": "1.07e-05"
    },
    "149032": {
        "Index": "149032",
        "ID": "99475",
        "Name": "Joel Michael Redhead",
        "Sex": "M",
        "Age": "26.0",
        "Height": "187.0",
        "Weight": "60.0",
        "Team": "Grenada",
        "NOC": "GRD",
        "Games": "2012 Summer",
        "Year": "2012",
        "Season": "Summer",
        "City": "London",
        "Sport": "Athletics",
        "Event": "Athletics Men's 200 metres",
        "Medal": "",
        "Host": "0",
        "Nat_Pop": "105481.0",
        "Global_Pop%": "1.49e-05",
        "Rural_Pop%": "64.399",
        "Life_Expect": "73.044",
        "GDP": "799882148.1",
        "GDP_Per_Cap": "7583.187001",
        "Global_GDP%": "1.07e-05"
    },
    "149179": {
        "Index": "149179",
        "ID": "99581",
        "Name": "Hazel-Ann Regis",
        "Sex": "F",
        "Age": "19.0",
        "Height": "157.0",
        "Weight": "64.0",
        "Team": "Grenada",
        "NOC": "GRD",
        "Games": "2000 Summer",
        "Year": "2000",
        "Season": "Summer",
        "City": "Sydney",
        "Sport": "Athletics",
        "Event": "Athletics Women's 400 metres",
        "Medal": "",
        "Host": "0",
        "Nat_Pop": "101619.0",
        "Global_Pop%": "1.66e-05",
        "Rural_Pop%": "64.129",
        "Life_Expect": "70.337",
        "GDP": "520044370.4",
        "GDP_Per_Cap": "5117.589923",
        "Global_GDP%": "1.55e-05"
    },
    "149180": {
        "Index": "149180",
        "ID": "99581",
        "Name": "Hazel-Ann Regis",
        "Sex": "F",
        "Age": "23.0",
        "Height": "157.0",
        "Weight": "64.0",
        "Team": "Grenada",
        "NOC": "GRD",
        "Games": "2004 Summer",
        "Year": "2004",
        "Season": "Summer",
        "City": "Athina",
        "Sport": "Athletics",
        "Event": "Athletics Women's 400 metres",
        "Medal": "",
        "Host": "0",
        "Nat_Pop": "102656.0",
        "Global_Pop%": "1.59e-05",
        "Rural_Pop%": "64.037",
        "Life_Expect": "71.213",
        "GDP": "599118592.6",
        "GDP_Per_Cap": "5836.177063",
        "Global_GDP%": "1.37e-05"
    },
    "153829": {
        "Index": "153829",
        "ID": "102708",
        "Name": "Shermaine Ross",
        "Sex": "F",
        "Age": "20.0",
        "Height": "",
        "Weight": "",
        "Team": "Grenada",
        "NOC": "GRD",
        "Games": "1992 Summer",
        "Year": "1992",
        "Season": "Summer",
        "City": "Barcelona",
        "Sport": "Athletics",
        "Event": "Athletics Women's 400 metres",
        "Medal": "",
        "Host": "0",
        "Nat_Pop": "97198.0",
        "Global_Pop%": "1.78e-05",
        "Rural_Pop%": "66.235",
        "Life_Expect": "68.925",
        "GDP": "310160444.4",
        "GDP_Per_Cap": "3191.016733",
        "Global_GDP%": "1.22e-05"
    },
    "159464": {
        "Index": "159464",
        "ID": "106345",
        "Name": "Samuel Sawny",
        "Sex": "M",
        "Age": "",
        "Height": "",
        "Weight": "",
        "Team": "Grenada",
        "NOC": "GRD",
        "Games": "1984 Summer",
        "Year": "1984",
        "Season": "Summer",
        "City": "Los Angeles",
        "Sport": "Athletics",
        "Event": "Athletics Men's 800 metres",
        "Medal": "",
        "Host": "0",
        "Nat_Pop": "98439.0",
        "Global_Pop%": "2.07e-05",
        "Rural_Pop%": "66.865",
        "Life_Expect": "67.449",
        "GDP": "145533296.3",
        "GDP_Per_Cap": "1478.410958",
        "Global_GDP%": "1.2e-05"
    },
    "165771": {
        "Index": "165771",
        "ID": "110657",
        "Name": "Gabriel Simeon",
        "Sex": "M",
        "Age": "20.0",
        "Height": "",
        "Weight": "",
        "Team": "Grenada",
        "NOC": "GRD",
        "Games": "1992 Summer",
        "Year": "1992",
        "Season": "Summer",
        "City": "Barcelona",
        "Sport": "Athletics",
        "Event": "Athletics Men's 100 metres",
        "Medal": "",
        "Host": "0",
        "Nat_Pop": "97198.0",
        "Global_Pop%": "1.78e-05",
        "Rural_Pop%": "66.235",
        "Life_Expect": "68.925",
        "GDP": "310160444.4",
        "GDP_Per_Cap": "3191.016733",
        "Global_GDP%": "1.22e-05"
    },
    "165772": {
        "Index": "165772",
        "ID": "110657",
        "Name": "Gabriel Simeon",
        "Sex": "M",
        "Age": "20.0",
        "Height": "",
        "Weight": "",
        "Team": "Grenada",
        "NOC": "GRD",
        "Games": "1992 Summer",
        "Year": "1992",
        "Season": "Summer",
        "City": "Barcelona",
        "Sport": "Athletics",
        "Event": "Athletics Men's 200 metres",
        "Medal": "",
        "Host": "0",
        "Nat_Pop": "97198.0",
        "Global_Pop%": "1.78e-05",
        "Rural_Pop%": "66.235",
        "Life_Expect": "68.925",
        "GDP": "310160444.4",
        "GDP_Per_Cap": "3191.016733",
        "Global_GDP%": "1.22e-05"
    },
    "166098": {
        "Index": "166098",
        "ID": "110878",
        "Name": "Esau Walter Simpson",
        "Sex": "M",
        "Age": "21.0",
        "Height": "185.0",
        "Weight": "75.0",
        "Team": "Grenada",
        "NOC": "GRD",
        "Games": "2012 Summer",
        "Year": "2012",
        "Season": "Summer",
        "City": "London",
        "Sport": "Swimming",
        "Event": "Swimming Men's 100 metres Freestyle",
        "Medal": "",
        "Host": "0",
        "Nat_Pop": "105481.0",
        "Global_Pop%": "1.49e-05",
        "Rural_Pop%": "64.399",
        "Life_Expect": "73.044",
        "GDP": "799882148.1",
        "GDP_Per_Cap": "7583.187001",
        "Global_GDP%": "1.07e-05"
    },
    "170829": {
        "Index": "170829",
        "ID": "114082",
        "Name": "Andrea St Bernard",
        "Sex": "F",
        "Age": "32.0",
        "Height": "175.0",
        "Weight": "66.0",
        "Team": "Grenada",
        "NOC": "GRD",
        "Games": "2012 Summer",
        "Year": "2012",
        "Season": "Summer",
        "City": "London",
        "Sport": "Taekwondo",
        "Event": "Taekwondo Women's Welterweight",
        "Medal": "",
        "Host": "0",
        "Nat_Pop": "105481.0",
        "Global_Pop%": "1.49e-05",
        "Rural_Pop%": "64.399",
        "Life_Expect": "73.044",
        "GDP": "799882148.1",
        "GDP_Per_Cap": "7583.187001",
        "Global_GDP%": "1.07e-05"
    },
    "171634": {
        "Index": "171634",
        "ID": "114594",
        "Name": "Johnathan Andrew Steele",
        "Sex": "M",
        "Age": "20.0",
        "Height": "190.0",
        "Weight": "85.0",
        "Team": "Grenada",
        "NOC": "GRD",
        "Games": "2004 Summer",
        "Year": "2004",
        "Season": "Summer",
        "City": "Athina",
        "Sport": "Swimming",
        "Event": "Swimming Men's 50 metres Freestyle",
        "Medal": "",
        "Host": "0",
        "Nat_Pop": "102656.0",
        "Global_Pop%": "1.59e-05",
        "Rural_Pop%": "64.037",
        "Life_Expect": "71.213",
        "GDP": "599118592.6",
        "GDP_Per_Cap": "5836.177063",
        "Global_GDP%": "1.37e-05"
    },
    "175787": {
        "Index": "175787",
        "ID": "117229",
        "Name": "Rudieon \"Rudy\" Sylvan",
        "Sex": "M",
        "Age": "21.0",
        "Height": "175.0",
        "Weight": "73.0",
        "Team": "Grenada",
        "NOC": "GRD",
        "Games": "2000 Summer",
        "Year": "2000",
        "Season": "Summer",
        "City": "Sydney",
        "Sport": "Athletics",
        "Event": "Athletics Men's 400 metres",
        "Medal": "",
        "Host": "0",
        "Nat_Pop": "101619.0",
        "Global_Pop%": "1.66e-05",
        "Rural_Pop%": "64.129",
        "Life_Expect": "70.337",
        "GDP": "520044370.4",
        "GDP_Per_Cap": "5117.589923",
        "Global_GDP%": "1.55e-05"
    },
    "175797": {
        "Index": "175797",
        "ID": "117238",
        "Name": "Patricia Sylvester (Cornwall-)",
        "Sex": "F",
        "Age": "25.0",
        "Height": "175.0",
        "Weight": "59.0",
        "Team": "Grenada",
        "NOC": "GRD",
        "Games": "2008 Summer",
        "Year": "2008",
        "Season": "Summer",
        "City": "Beijing",
        "Sport": "Athletics",
        "Event": "Athletics Women's Long Jump",
        "Medal": "",
        "Host": "0",
        "Nat_Pop": "103930.0",
        "Global_Pop%": "1.54e-05",
        "Rural_Pop%": "64.225",
        "Life_Expect": "72.142",
        "GDP": "825977888.9",
        "GDP_Per_Cap": "7947.444327",
        "Global_GDP%": "1.3e-05"
    },
    "177861": {
        "Index": "177861",
        "ID": "118543",
        "Name": "Bralon Shazam Taplin",
        "Sex": "M",
        "Age": "24.0",
        "Height": "180.0",
        "Weight": "75.0",
        "Team": "Grenada",
        "NOC": "GRD",
        "Games": "2016 Summer",
        "Year": "2016",
        "Season": "Summer",
        "City": "Rio de Janeiro",
        "Sport": "Athletics",
        "Event": "Athletics Men's 400 metres",
        "Medal": "",
        "Host": "0",
        "Nat_Pop": "107317.0",
        "Global_Pop%": "1.44e-05",
        "Rural_Pop%": "64.384",
        "Life_Expect": "73.659",
        "GDP": "1056188593.0",
        "GDP_Per_Cap": "9841.764054",
        "Global_GDP%": "1.39e-05"
    },
    "181040": {
        "Index": "181040",
        "ID": "120631",
        "Name": "John Tobin",
        "Sex": "M",
        "Age": "",
        "Height": "",
        "Weight": "",
        "Team": "Grenada",
        "NOC": "GRD",
        "Games": "1988 Summer",
        "Year": "1988",
        "Season": "Summer",
        "City": "Seoul",
        "Sport": "Boxing",
        "Event": "Boxing Men's Middleweight",
        "Medal": "",
        "Host": "0",
        "Nat_Pop": "98062.0",
        "Global_Pop%": "1.92e-05",
        "Rural_Pop%": "66.67",
        "Life_Expect": "68.247",
        "GDP": "236357518.5",
        "GDP_Per_Cap": "2410.286538",
        "Global_GDP%": "1.24e-05"
    },
    "189595": {
        "Index": "189595",
        "ID": "126339",
        "Name": "Lindon Victor",
        "Sex": "M",
        "Age": "23.0",
        "Height": "",
        "Weight": "",
        "Team": "Grenada",
        "NOC": "GRD",
        "Games": "2016 Summer",
        "Year": "2016",
        "Season": "Summer",
        "City": "Rio de Janeiro",
        "Sport": "Athletics",
        "Event": "Athletics Men's Decathlon",
        "Medal": "",
        "Host": "0",
        "Nat_Pop": "107317.0",
        "Global_Pop%": "1.44e-05",
        "Rural_Pop%": "64.384",
        "Life_Expect": "73.659",
        "GDP": "1056188593.0",
        "GDP_Per_Cap": "9841.764054",
        "Global_GDP%": "1.39e-05"
    },
    "190147": {
        "Index": "190147",
        "ID": "126719",
        "Name": "Arlene Vincent Mark",
        "Sex": "F",
        "Age": "33.0",
        "Height": "",
        "Weight": "",
        "Team": "Grenada",
        "NOC": "GRD",
        "Games": "1988 Summer",
        "Year": "1988",
        "Season": "Summer",
        "City": "Seoul",
        "Sport": "Athletics",
        "Event": "Athletics Women's Marathon",
        "Medal": "",
        "Host": "0",
        "Nat_Pop": "98062.0",
        "Global_Pop%": "1.92e-05",
        "Rural_Pop%": "66.67",
        "Life_Expect": "68.247",
        "GDP": "236357518.5",
        "GDP_Per_Cap": "2410.286538",
        "Global_GDP%": "1.24e-05"
    },
    "195602": {
        "Index": "195602",
        "ID": "130572",
        "Name": "Clint Williams",
        "Sex": "M",
        "Age": "19.0",
        "Height": "",
        "Weight": "",
        "Team": "Grenada",
        "NOC": "GRD",
        "Games": "1996 Summer",
        "Year": "1996",
        "Season": "Summer",
        "City": "Atlanta",
        "Sport": "Athletics",
        "Event": "Athletics Men's 4 x 400 metres Relay",
        "Medal": "",
        "Host": "0",
        "Nat_Pop": "100796.0",
        "Global_Pop%": "1.74e-05",
        "Rural_Pop%": "65.189",
        "Life_Expect": "69.57",
        "GDP": "366911444.4",
        "GDP_Per_Cap": "3640.138938",
        "Global_GDP%": "1.16e-05"
    },
    "195723": {
        "Index": "195723",
        "ID": "130649",
        "Name": "Paul Williams",
        "Sex": "M",
        "Age": "26.0",
        "Height": "191.0",
        "Weight": "85.0",
        "Team": "Grenada",
        "NOC": "GRD",
        "Games": "2012 Summer",
        "Year": "2012",
        "Season": "Summer",
        "City": "London",
        "Sport": "Athletics",
        "Event": "Athletics Men's 100 metres",
        "Medal": "",
        "Host": "0",
        "Nat_Pop": "105481.0",
        "Global_Pop%": "1.49e-05",
        "Rural_Pop%": "64.399",
        "Life_Expect": "73.044",
        "GDP": "799882148.1",
        "GDP_Per_Cap": "7583.187001",
        "Global_GDP%": "1.07e-05"
    },
    "195952": {
        "Index": "195952",
        "ID": "130793",
        "Name": "Bernard Wilson",
        "Sex": "M",
        "Age": "",
        "Height": "",
        "Weight": "",
        "Team": "Grenada",
        "NOC": "GRD",
        "Games": "1984 Summer",
        "Year": "1984",
        "Season": "Summer",
        "City": "Los Angeles",
        "Sport": "Boxing",
        "Event": "Boxing Men's Welterweight",
        "Medal": "",
        "Host": "0",
        "Nat_Pop": "98439.0",
        "Global_Pop%": "2.07e-05",
        "Rural_Pop%": "66.865",
        "Life_Expect": "67.449",
        "GDP": "145533296.3",
        "GDP_Per_Cap": "1478.410958",
        "Global_GDP%": "1.2e-05"
    }
}