{
    "Athletics": {
        "Index": "156994",
        "Name": "Ahmed Mohamed Sallouma",
        "Sex": "M",
        "Age": "",
        "Height": "168.0",
        "Weight": "63.0",
        "Team": "Libya",
        "NOC": "LBY",
        "Year": "1980",
        "Sport": "Athletics",
        "Medal": "",
        "Host": "0",
        "Nat_Pop": "3219466.0",
        "Global_Pop%": "0.000725482",
        "Rural_Pop%": "29.906",
        "Life_Expect": "64.185",
        "GDP": "",
        "GDP_Per_Cap": "0",
        "Global_GDP%": ""
    },
    "Cycling": {
        "Index": "163815",
        "Name": "Khalid Shebani",
        "Sex": "M",
        "Age": "",
        "Height": "167.0",
        "Weight": "67.0",
        "Team": "Libya",
        "NOC": "LBY",
        "Year": "1980",
        "Sport": "Cycling",
        "Medal": "",
        "Host": "0",
        "Nat_Pop": "3219466.0",
        "Global_Pop%": "0.000725482",
        "Rural_Pop%": "29.906",
        "Life_Expect": "64.185",
        "GDP": "",
        "GDP_Per_Cap": "0",
        "Global_GDP%": ""
    },
    "Weightlifting": {
        "Index": "163372",
        "Name": "Ali Shalabi",
        "Sex": "M",
        "Age": "",
        "Height": "160.0",
        "Weight": "56.0",
        "Team": "Libya",
        "NOC": "LBY",
        "Year": "1980",
        "Sport": "Weightlifting",
        "Medal": "",
        "Host": "0",
        "Nat_Pop": "3219466.0",
        "Global_Pop%": "0.000725482",
        "Rural_Pop%": "29.906",
        "Life_Expect": "64.185",
        "GDP": "",
        "GDP_Per_Cap": "0",
        "Global_GDP%": ""
    },
    "Swimming": {
        "Index": "194407",
        "Name": "Abdulwahab Werfeli",
        "Sex": "M",
        "Age": "",
        "Height": "178.0",
        "Weight": "71.0",
        "Team": "Libya",
        "NOC": "LBY",
        "Year": "1980",
        "Sport": "Swimming",
        "Medal": "",
        "Host": "0",
        "Nat_Pop": "3219466.0",
        "Global_Pop%": "0.000725482",
        "Rural_Pop%": "29.906",
        "Life_Expect": "64.185",
        "GDP": "",
        "GDP_Per_Cap": "0",
        "Global_GDP%": ""
    },
    "Judo": {
        "Index": "62647",
        "Name": "Yahia B. Gregni",
        "Sex": "M",
        "Age": "22.0",
        "Height": "",
        "Weight": "",
        "Team": "Libya",
        "NOC": "LBY",
        "Year": "1992",
        "Sport": "Judo",
        "Medal": "",
        "Host": "0",
        "Nat_Pop": "4651004.0",
        "Global_Pop%": "0.000852435",
        "Rural_Pop%": "24.168",
        "Life_Expect": "69.172",
        "GDP": "33881392045.0",
        "GDP_Per_Cap": "7284.747991",
        "Global_GDP%": "0.001333913"
    },
    "Volleyball": {
        "Index": "203506",
        "Name": "Ahmed Zoubi",
        "Sex": "M",
        "Age": "",
        "Height": "",
        "Weight": "",
        "Team": "Libya",
        "NOC": "LBY",
        "Year": "1980",
        "Sport": "Volleyball",
        "Medal": "",
        "Host": "0",
        "Nat_Pop": "3219466.0",
        "Global_Pop%": "0.000725482",
        "Rural_Pop%": "29.906",
        "Life_Expect": "64.185",
        "GDP": "",
        "GDP_Per_Cap": "0",
        "Global_GDP%": ""
    },
    "Archery": {
        "Index": "46450",
        "Name": "Ali Saleh El-Ghrari",
        "Sex": "M",
        "Age": "19.0",
        "Height": "",
        "Weight": "",
        "Team": "Libya",
        "NOC": "LBY",
        "Year": "2016",
        "Sport": "Archery",
        "Medal": "",
        "Host": "0",
        "Nat_Pop": "6293253.0",
        "Global_Pop%": "0.000845625",
        "Rural_Pop%": "21.246",
        "Life_Expect": "71.934",
        "GDP": "",
        "GDP_Per_Cap": "0",
        "Global_GDP%": ""
    },
    "Table Tennis": {
        "Index": "46548",
        "Name": "Attaher Mohamed El-Mahjoub",
        "Sex": "M",
        "Age": "",
        "Height": "",
        "Weight": "",
        "Team": "Libya",
        "NOC": "LBY",
        "Year": "1992",
        "Sport": "Table Tennis",
        "Medal": "",
        "Host": "0",
        "Nat_Pop": "4651004.0",
        "Global_Pop%": "0.000852435",
        "Rural_Pop%": "24.168",
        "Life_Expect": "69.172",
        "GDP": "33881392045.0",
        "GDP_Per_Cap": "7284.747991",
        "Global_GDP%": "0.001333913"
    },
    "Rowing": {
        "Index": "55999",
        "Name": "Hussein Gambour",
        "Sex": "M",
        "Age": "26.0",
        "Height": "175.0",
        "Weight": "68.0",
        "Team": "Libya",
        "NOC": "LBY",
        "Year": "2016",
        "Sport": "Rowing",
        "Medal": "",
        "Host": "0",
        "Nat_Pop": "6293253.0",
        "Global_Pop%": "0.000845625",
        "Rural_Pop%": "21.246",
        "Life_Expect": "71.934",
        "GDP": "",
        "GDP_Per_Cap": "0",
        "Global_GDP%": ""
    },
    "Taekwondo": {
        "Index": "180981",
        "Name": "Salem Ezedin Tlish",
        "Sex": "M",
        "Age": "22.0",
        "Height": "169.0",
        "Weight": "68.0",
        "Team": "Libya",
        "NOC": "LBY",
        "Year": "2004",
        "Sport": "Taekwondo",
        "Medal": "",
        "Host": "0",
        "Nat_Pop": "5704759.0",
        "Global_Pop%": "0.000886335",
        "Rural_Pop%": "23.226",
        "Life_Expect": "71.17",
        "GDP": "33122307692.0",
        "GDP_Per_Cap": "5806.083604",
        "Global_GDP%": "0.000756217"
    }
}